{
  "atual": {
    "data": "04 abril 2026",
    "data_simples": "04/04/2026",
    "registros": [
      {
        "data": "04 abril 2026",
        "email": "",
        "horario": "08:00/13:00",
        "phone": "",
        "pos_x": 92,
        "profissional": "Marcia de Menezes Bergamo",
        "setor": "Alojamento Conjunto",
        "tipo_turno": "Rotina - Alojamento Conjunto - Final de Semana"
      },
      {
        "data": "04 abril 2026",
        "email": "",
        "horario": "07:00/07:00",
        "phone": "",
        "pos_x": 429,
        "profissional": "Angela Aiolfi",
        "setor": "Bucomaxilo Sobreaviso",
        "tipo_turno": "Bucomaxilo - Sobreaviso"
      },
      {
        "data": "04 abril 2026",
        "email": "",
        "horario": "07:00/07:00",
        "phone": "",
        "pos_x": 767,
        "profissional": "Thais Nascimento Helou",
        "setor": "Cardiologia - Sobreaviso",
        "tipo_turno": "Sobreaviso Cardiologia"
      },
      {
        "data": "04 abril 2026",
        "email": "",
        "horario": "07:00/07:00",
        "phone": "",
        "pos_x": 1104,
        "profissional": "Mateus Ceresoli Baptistella",
        "setor": "Cirurgia Geral - Sobreaviso",
        "tipo_turno": "Cirurgia Geral - Sobreaviso"
      },
      {
        "data": "04 abril 2026",
        "email": "",
        "horario": "08:00/08:00",
        "phone": "",
        "pos_x": 1441,
        "profissional": "Alberto Stolt",
        "setor": "Cirurgia Pediátrica - Sobreaviso",
        "tipo_turno": "Sobreaviso Cirurgia Pediátrica"
      },
      {
        "data": "04 abril 2026",
        "email": "",
        "horario": "08:00/08:00",
        "phone": "",
        "pos_x": 1779,
        "profissional": "Dantas Luis Lavall da Silva",
        "setor": "Cirurgia Torácica - Sobreaviso",
        "tipo_turno": "Cirurgia Torácica - Sobreaviso"
      },
      {
        "data": "04 abril 2026",
        "email": "",
        "horario": "08:00/08:00",
        "phone": "",
        "pos_x": 2116,
        "profissional": "Graciany Gasperin",
        "setor": "Cirurgia Vascular - Sobreaviso",
        "tipo_turno": "Vascular Sobreaviso"
      },
      {
        "data": "04 abril 2026",
        "email": "",
        "horario": "08:00/14:00",
        "phone": "",
        "pos_x": 2453,
        "profissional": "Eduardo Formoso Goldschimidt",
        "setor": "Clínica Médica",
        "tipo_turno": "Rotina Finais de Semana"
      },
      {
        "data": "04 abril 2026",
        "email": "",
        "horario": "08:00/08:00",
        "phone": "",
        "pos_x": 2790,
        "profissional": "Maridiane Tormem",
        "setor": "Endoscopia - Sobreaviso",
        "tipo_turno": "Endoscopia - Sobreaviso"
      },
      {
        "data": "04 abril 2026",
        "email": "",
        "horario": "07:00/13:00",
        "phone": "",
        "pos_x": 3128,
        "profissional": "Ana Claudia Cazzuni",
        "setor": "Ginecologia e Obstetrícia - Plantão",
        "tipo_turno": "Plantão Matutino - P1"
      },
      {
        "data": "04 abril 2026",
        "email": "",
        "horario": "07:00/13:00",
        "phone": "",
        "pos_x": 3128,
        "profissional": "Ocieny Gonzaga Guimarães Ramírez",
        "setor": "Ginecologia e Obstetrícia - Plantão",
        "tipo_turno": "Plantão Matutino - P2"
      },
      {
        "data": "04 abril 2026",
        "email": "",
        "horario": "07:00/07:00",
        "phone": "",
        "pos_x": 3465,
        "profissional": "Julio Roberto Barbiero",
        "setor": "Hemodinâmica - Sobreaviso Cardiologia",
        "tipo_turno": "Hemodinâmica - Sobreaviso"
      },
      {
        "data": "04 abril 2026",
        "email": "",
        "horario": "07:00/13:00",
        "phone": "",
        "pos_x": 3802,
        "profissional": "Bruno Taddeo Nogueira Alves Soares De Alvarenga",
        "setor": "Hospitalista",
        "tipo_turno": "Hospitalista Comanejo Matutino"
      },
      {
        "data": "04 abril 2026",
        "email": "",
        "horario": "07:00/13:00",
        "phone": "",
        "pos_x": 3802,
        "profissional": "Samuel Teixeira Coelho",
        "setor": "Hospitalista",
        "tipo_turno": "Hospitalista Urgência Matutino"
      },
      {
        "data": "04 abril 2026",
        "email": "",
        "horario": "06:00/14:00",
        "phone": "",
        "pos_x": 4140,
        "profissional": "Geraldo Antunes Cordova",
        "setor": "Nefrologia - Sobreaviso",
        "tipo_turno": "Matutino"
      },
      {
        "data": "04 abril 2026",
        "email": "",
        "horario": "07:00/07:00",
        "phone": "",
        "pos_x": 4477,
        "profissional": "Rafael Cordeiro dos Santos",
        "setor": "Neurocirurgia - Sobreaviso",
        "tipo_turno": "Neurocirurgia - Sobreaviso"
      },
      {
        "data": "04 abril 2026",
        "email": "",
        "horario": "07:00/07:00",
        "phone": "",
        "pos_x": 4814,
        "profissional": "Marcelo Lemos Vieira Da Cunha",
        "setor": "Neurologia/U-AVC Integral - Sobreaviso",
        "tipo_turno": "Neurologia/U-AVC Integral - Sobreaviso"
      },
      {
        "data": "04 abril 2026",
        "email": "",
        "horario": "07:00/07:00",
        "phone": "",
        "pos_x": 5152,
        "profissional": "Davi Machado de Souza",
        "setor": "Oftalmologia Sobreaviso",
        "tipo_turno": "Sobreaviso Oftalmologia"
      },
      {
        "data": "04 abril 2026",
        "email": "",
        "horario": "07:00/19:00",
        "phone": "",
        "pos_x": 5489,
        "profissional": "Kaliandra de Almeida",
        "setor": "Oncologia Pediátrica - Sobreaviso",
        "tipo_turno": "Sobreaviso Oncologia"
      },
      {
        "data": "04 abril 2026",
        "email": "",
        "horario": "07:00/07:00",
        "phone": "",
        "pos_x": 5826,
        "profissional": "Julio Cesar Dalferth de Oliveira",
        "setor": "Ortopedia e Traumatologia - Sobreaviso",
        "tipo_turno": "Ortopedia  Sobreaviso - Equipe 1"
      },
      {
        "data": "04 abril 2026",
        "email": "",
        "horario": "07:00/07:00",
        "phone": "",
        "pos_x": 5826,
        "profissional": "Ricardo da Silva Penteado Junior",
        "setor": "Ortopedia e Traumatologia - Sobreaviso",
        "tipo_turno": "Ortopedia Sobreaviso  - Equipe 2"
      },
      {
        "data": "04 abril 2026",
        "email": "",
        "horario": "07:00/15:00",
        "phone": "",
        "pos_x": 6164,
        "profissional": "Fernanda Trevisan Zancan",
        "setor": "Residência de Clínica Médica",
        "tipo_turno": "Res. Clinica Méidica Intermediário"
      },
      {
        "data": "04 abril 2026",
        "email": "",
        "horario": "07:00/19:00",
        "phone": "",
        "pos_x": 6164,
        "profissional": "Ligia Oro",
        "setor": "Residência de Clínica Médica",
        "tipo_turno": "Res. Clínica Médica"
      },
      {
        "data": "04 abril 2026",
        "email": "",
        "horario": "07:00/19:00",
        "phone": "",
        "pos_x": 6501,
        "profissional": "Ana Catarina Dantas Gomes",
        "setor": "Residência de Cirurgia Geral",
        "tipo_turno": "DIA"
      },
      {
        "data": "04 abril 2026",
        "email": "",
        "horario": "07:00/13:00",
        "phone": "",
        "pos_x": 6838,
        "profissional": "Priscila Domingos",
        "setor": "Serviço de Urgência e Emergência",
        "tipo_turno": "P1 - EMERGÊNCIA"
      },
      {
        "data": "04 abril 2026",
        "email": "",
        "horario": "07:00/13:00",
        "phone": "",
        "pos_x": 6838,
        "profissional": "Erika Luiza Biasoli",
        "setor": "Serviço de Urgência e Emergência",
        "tipo_turno": "P2 - PRONTO ATENDIMENTO"
      },
      {
        "data": "04 abril 2026",
        "email": "",
        "horario": "10:00/16:00",
        "phone": "",
        "pos_x": 6838,
        "profissional": "Marta Schmidt Pfaffenzeller",
        "setor": "Serviço de Urgência e Emergência",
        "tipo_turno": "P3 - REFORÇO"
      },
      {
        "data": "04 abril 2026",
        "email": "",
        "horario": "07:00/07:00",
        "phone": "",
        "pos_x": 7176,
        "profissional": "Mario Goto",
        "setor": "Transplante - Sobreaviso Cirurgia",
        "tipo_turno": "Cirurgia Geral - 1"
      },
      {
        "data": "04 abril 2026",
        "email": "",
        "horario": "07:00/07:00",
        "phone": "",
        "pos_x": 7176,
        "profissional": "Thiago Felippe Reck",
        "setor": "Transplante - Sobreaviso Cirurgia",
        "tipo_turno": "Cirurgia Geral - 2"
      },
      {
        "data": "04 abril 2026",
        "email": "",
        "horario": "07:00/07:00",
        "phone": "",
        "pos_x": 7176,
        "profissional": "Juliano Ferneda",
        "setor": "Transplante - Sobreaviso Cirurgia",
        "tipo_turno": "Urologia"
      },
      {
        "data": "04 abril 2026",
        "email": "",
        "horario": "07:30/07:30",
        "phone": "",
        "pos_x": 7513,
        "profissional": "João Roberto Munhoz Zorzetto",
        "setor": "Ultrassonografia - Sobreaviso",
        "tipo_turno": "Ultrassonografia - Sobreaviso Final de Semana"
      },
      {
        "data": "04 abril 2026",
        "email": "",
        "horario": "07:00/13:00",
        "phone": "",
        "pos_x": 7850,
        "profissional": "Bruna Bassotti Favretto",
        "setor": "Unidade de Cuidados Intermediários Neonatais - UCINCo E Sala de Parto - Escala Médica",
        "tipo_turno": "Plantão - Matutino"
      },
      {
        "data": "04 abril 2026",
        "email": "",
        "horario": "07:00/13:00",
        "phone": "",
        "pos_x": 8187,
        "profissional": "Adelaine Marilia Pinheiro",
        "setor": "Unidade de Terapia Intensiva (UTI) Adulto I",
        "tipo_turno": "Matutino"
      },
      {
        "data": "04 abril 2026",
        "email": "",
        "horario": "07:00/13:00",
        "phone": "",
        "pos_x": 8525,
        "profissional": "Matheus De Oliveira Brock",
        "setor": "Unidade de Terapia Intensiva (UTI) Adulto II",
        "tipo_turno": "Matutino"
      },
      {
        "data": "04 abril 2026",
        "email": "",
        "horario": "07:00/13:00",
        "phone": "",
        "pos_x": 8862,
        "profissional": "Cesar Augusto Seidler Junior",
        "setor": "Unidade de Terapia Intensiva (UTI) Adulto III",
        "tipo_turno": "Matutino"
      },
      {
        "data": "04 abril 2026",
        "email": "",
        "horario": "07:00/12:00",
        "phone": "",
        "pos_x": 9199,
        "profissional": "Lisane Beatriz Giacomossi",
        "setor": "Unidade de Terapia Intensiva (UTI) Neonatal - Plantão - Escala Médica",
        "tipo_turno": "Rotina"
      },
      {
        "data": "04 abril 2026",
        "email": "",
        "horario": "07:00/13:00",
        "phone": "",
        "pos_x": 9199,
        "profissional": "Fabiele Bandeira",
        "setor": "Unidade de Terapia Intensiva (UTI) Neonatal - Plantão - Escala Médica",
        "tipo_turno": "Matutino"
      },
      {
        "data": "04 abril 2026",
        "email": "",
        "horario": "07:00/07:00",
        "phone": "",
        "pos_x": 9537,
        "profissional": "Vinicius Rubin",
        "setor": "Urologia Sobreaviso",
        "tipo_turno": "Sobreaviso Urologia"
      },
      {
        "data": "04 abril 2026",
        "email": "",
        "horario": "13:00/19:00",
        "phone": "",
        "pos_x": 3128,
        "profissional": "Ana Claudia Cazzuni",
        "setor": "Ginecologia e Obstetrícia - Plantão",
        "tipo_turno": "Plantão Vespertino - P1"
      },
      {
        "data": "04 abril 2026",
        "email": "",
        "horario": "13:00/19:00",
        "phone": "",
        "pos_x": 3128,
        "profissional": "Ocieny Gonzaga Guimarães Ramírez",
        "setor": "Ginecologia e Obstetrícia - Plantão",
        "tipo_turno": "Plantão Vespertino - P2"
      },
      {
        "data": "04 abril 2026",
        "email": "",
        "horario": "19:00/07:00",
        "phone": "",
        "pos_x": 3128,
        "profissional": "Morgana Filippi Chiella",
        "setor": "Ginecologia e Obstetrícia - Plantão",
        "tipo_turno": "Plantão Noturno - P1"
      },
      {
        "data": "04 abril 2026",
        "email": "",
        "horario": "19:00/07:00",
        "phone": "",
        "pos_x": 3128,
        "profissional": "Gabrielle Trevisan",
        "setor": "Ginecologia e Obstetrícia - Plantão",
        "tipo_turno": "Plantão Noturno - P1"
      },
      {
        "data": "04 abril 2026",
        "email": "",
        "horario": "13:00/19:00",
        "phone": "",
        "pos_x": 3802,
        "profissional": "Samuel Teixeira Coelho",
        "setor": "Hospitalista",
        "tipo_turno": "Hospitalista Urgência Vespertino"
      },
      {
        "data": "04 abril 2026",
        "email": "",
        "horario": "19:00/07:00",
        "phone": "",
        "pos_x": 3802,
        "profissional": "Eduardo Masiero Cola",
        "setor": "Hospitalista",
        "tipo_turno": "Noturno"
      },
      {
        "data": "04 abril 2026",
        "email": "",
        "horario": "14:00/06:00",
        "phone": "",
        "pos_x": 4140,
        "profissional": "Marcelo Eduardo Heinig",
        "setor": "Nefrologia - Sobreaviso",
        "tipo_turno": "Vesp - Noturno"
      },
      {
        "data": "04 abril 2026",
        "email": "",
        "horario": "19:00/07:00",
        "phone": "",
        "pos_x": 5489,
        "profissional": "Kaliandra de Almeida",
        "setor": "Oncologia Pediátrica - Sobreaviso",
        "tipo_turno": "Sobreaviso Oncologia"
      },
      {
        "data": "04 abril 2026",
        "email": "",
        "horario": "19:00/07:00",
        "phone": "",
        "pos_x": 6164,
        "profissional": "Cesar Augusto Seidler Junior",
        "setor": "Residência de Clínica Médica",
        "tipo_turno": "Res. Clínica Médica Noturno"
      },
      {
        "data": "04 abril 2026",
        "email": "",
        "horario": "19:00/07:00",
        "phone": "",
        "pos_x": 6164,
        "profissional": "Matheus Piton",
        "setor": "Residência de Clínica Médica",
        "tipo_turno": "Res. Clinica Méidica Intermediário"
      },
      {
        "data": "04 abril 2026",
        "email": "",
        "horario": "19:00/07:00",
        "phone": "",
        "pos_x": 6501,
        "profissional": "Ana Catarina Dantas Gomes",
        "setor": "Residência de Cirurgia Geral",
        "tipo_turno": "NOITE"
      },
      {
        "data": "04 abril 2026",
        "email": "",
        "horario": "13:00/19:00",
        "phone": "",
        "pos_x": 6838,
        "profissional": "Priscila Domingos",
        "setor": "Serviço de Urgência e Emergência",
        "tipo_turno": "P1 - EMERGÊNCIA"
      },
      {
        "data": "04 abril 2026",
        "email": "",
        "horario": "13:00/19:00",
        "phone": "",
        "pos_x": 6838,
        "profissional": "Brenda Lesley Alves Capra",
        "setor": "Serviço de Urgência e Emergência",
        "tipo_turno": "P2 - PRONTO ATENDIMENTO"
      },
      {
        "data": "04 abril 2026",
        "email": "",
        "horario": "14:00/22:00",
        "phone": "",
        "pos_x": 6838,
        "profissional": "Luiza da Ros Schumacher",
        "setor": "Serviço de Urgência e Emergência",
        "tipo_turno": "P4 - REFORÇO FDS"
      },
      {
        "data": "04 abril 2026",
        "email": "",
        "horario": "16:00/22:00",
        "phone": "",
        "pos_x": 6838,
        "profissional": "Bianca Soder  Wolschick",
        "setor": "Serviço de Urgência e Emergência",
        "tipo_turno": "P3 - REFORÇO"
      },
      {
        "data": "04 abril 2026",
        "email": "",
        "horario": "19:00/07:00",
        "phone": "",
        "pos_x": 6838,
        "profissional": "William Vinicius Weber",
        "setor": "Serviço de Urgência e Emergência",
        "tipo_turno": "P1 - EMERGÊNCIA"
      },
      {
        "data": "04 abril 2026",
        "email": "",
        "horario": "19:00/07:00",
        "phone": "",
        "pos_x": 6838,
        "profissional": "Izadora Valdameri Sulzbacher",
        "setor": "Serviço de Urgência e Emergência",
        "tipo_turno": "P2 - PRONTO ATENDIMENTO"
      },
      {
        "data": "04 abril 2026",
        "email": "",
        "horario": "13:00/19:00",
        "phone": "",
        "pos_x": 7850,
        "profissional": "Bruna Bassotti Favretto",
        "setor": "Unidade de Cuidados Intermediários Neonatais - UCINCo E Sala de Parto - Escala Médica",
        "tipo_turno": "Plantão - Vespertino"
      },
      {
        "data": "04 abril 2026",
        "email": "",
        "horario": "13:00/19:00",
        "phone": "",
        "pos_x": 7850,
        "profissional": "Lisane Beatriz Giacomossi",
        "setor": "Unidade de Cuidados Intermediários Neonatais - UCINCo E Sala de Parto - Escala Médica",
        "tipo_turno": "Rotina UCIN - Finais de Semana"
      },
      {
        "data": "04 abril 2026",
        "email": "",
        "horario": "19:00/07:00",
        "phone": "",
        "pos_x": 7850,
        "profissional": "Luiz Tsuyoshi Inoue",
        "setor": "Unidade de Cuidados Intermediários Neonatais - UCINCo E Sala de Parto - Escala Médica",
        "tipo_turno": "Plantão - Noturno"
      },
      {
        "data": "04 abril 2026",
        "email": "",
        "horario": "13:00/19:00",
        "phone": "",
        "pos_x": 8187,
        "profissional": "Adelaine Marilia Pinheiro",
        "setor": "Unidade de Terapia Intensiva (UTI) Adulto I",
        "tipo_turno": "Vespertino"
      },
      {
        "data": "04 abril 2026",
        "email": "",
        "horario": "13:30/14:30",
        "phone": "",
        "pos_x": 8187,
        "profissional": "Maiara Szepilowski Bampi",
        "setor": "Unidade de Terapia Intensiva (UTI) Adulto I",
        "tipo_turno": "Rotina Vespertino - Final de semana"
      },
      {
        "data": "04 abril 2026",
        "email": "",
        "horario": "19:00/07:00",
        "phone": "",
        "pos_x": 8187,
        "profissional": "Samantha de Aspiazu Damiani",
        "setor": "Unidade de Terapia Intensiva (UTI) Adulto I",
        "tipo_turno": "Noturno"
      },
      {
        "data": "04 abril 2026",
        "email": "",
        "horario": "13:00/19:00",
        "phone": "",
        "pos_x": 8525,
        "profissional": "Matheus De Oliveira Brock",
        "setor": "Unidade de Terapia Intensiva (UTI) Adulto II",
        "tipo_turno": "Vespertino"
      },
      {
        "data": "04 abril 2026",
        "email": "",
        "horario": "14:30/15:30",
        "phone": "",
        "pos_x": 8525,
        "profissional": "Maiara Szepilowski Bampi",
        "setor": "Unidade de Terapia Intensiva (UTI) Adulto II",
        "tipo_turno": "Rotina Vespertino- Final de Semana"
      },
      {
        "data": "04 abril 2026",
        "email": "",
        "horario": "19:00/07:00",
        "phone": "",
        "pos_x": 8525,
        "profissional": "Michel Peruzzo",
        "setor": "Unidade de Terapia Intensiva (UTI) Adulto II",
        "tipo_turno": "Noturno"
      },
      {
        "data": "04 abril 2026",
        "email": "",
        "horario": "13:00/19:00",
        "phone": "",
        "pos_x": 8862,
        "profissional": "Cesar Augusto Seidler Junior",
        "setor": "Unidade de Terapia Intensiva (UTI) Adulto III",
        "tipo_turno": "Vespertino"
      },
      {
        "data": "04 abril 2026",
        "email": "",
        "horario": "13:30/14:30",
        "phone": "",
        "pos_x": 8862,
        "profissional": "Maiara Szepilowski Bampi",
        "setor": "Unidade de Terapia Intensiva (UTI) Adulto III",
        "tipo_turno": "Rotina Vespertino - Final de Semana"
      },
      {
        "data": "04 abril 2026",
        "email": "",
        "horario": "19:00/07:00",
        "phone": "",
        "pos_x": 8862,
        "profissional": "Elaine Aparecida Forgiarini",
        "setor": "Unidade de Terapia Intensiva (UTI) Adulto III",
        "tipo_turno": "Noturno"
      },
      {
        "data": "04 abril 2026",
        "email": "",
        "horario": "13:00/19:00",
        "phone": "",
        "pos_x": 9199,
        "profissional": "Fabiele Bandeira",
        "setor": "Unidade de Terapia Intensiva (UTI) Neonatal - Plantão - Escala Médica",
        "tipo_turno": "Vespertino"
      },
      {
        "data": "04 abril 2026",
        "email": "",
        "horario": "19:00/07:00",
        "phone": "",
        "pos_x": 9199,
        "profissional": "Fabiane Scheffer Reginatto",
        "setor": "Unidade de Terapia Intensiva (UTI) Neonatal - Plantão - Escala Médica",
        "tipo_turno": "Noturno"
      },
      {
        "data": "04 abril 2026",
        "email": "",
        "horario": "07:00/08:00",
        "phone": "",
        "pos_x": 7850,
        "profissional": "Marcia de Menezes Bergamo",
        "setor": "Unidade de Cuidados Intermediários Neonatais - UCINCo E Sala de Parto - Escala Médica",
        "tipo_turno": "Rotina UCIN - Finais de Semana Matutino"
      },
      {
        "data": "04 abril 2026",
        "email": "",
        "horario": "07:30/08:30",
        "phone": "",
        "pos_x": 8187,
        "profissional": "Maiara Szepilowski Bampi",
        "setor": "Unidade de Terapia Intensiva (UTI) Adulto I",
        "tipo_turno": "Rotina Matutino - Final de Semana"
      },
      {
        "data": "04 abril 2026",
        "email": "",
        "horario": "08:30/09:30",
        "phone": "",
        "pos_x": 8525,
        "profissional": "Maiara Szepilowski Bampi",
        "setor": "Unidade de Terapia Intensiva (UTI) Adulto II",
        "tipo_turno": "Rotina Matutino - Final de Semana"
      },
      {
        "data": "04 abril 2026",
        "email": "",
        "horario": "07:30/08:30",
        "phone": "",
        "pos_x": 8862,
        "profissional": "Maiara Szepilowski Bampi",
        "setor": "Unidade de Terapia Intensiva (UTI) Adulto III",
        "tipo_turno": "Rotina Matutino - Final de Semana"
      }
    ],
    "total": 73
  },
  "anterior": {
    "data": "03 abril 2026",
    "data_simples": "03/04/2026",
    "registros": [
      {
        "data": "03 abril 2026",
        "email": "",
        "horario": "07:00/13:00",
        "phone": "",
        "pos_x": 92,
        "profissional": "Fabiane Scheffer Reginatto",
        "setor": "Alojamento Conjunto",
        "tipo_turno": "Rotina - Alojamento Conjunto"
      },
      {
        "data": "03 abril 2026",
        "email": "",
        "horario": "08:00/12:00",
        "phone": "",
        "pos_x": 429,
        "profissional": "Patricia Carla De Lima",
        "setor": "Ambulatório De Oncologia Pediátrica",
        "tipo_turno": "Ambulatório de Oncologia"
      },
      {
        "data": "03 abril 2026",
        "email": "",
        "horario": "07:00/07:00",
        "phone": "",
        "pos_x": 766,
        "profissional": "Angela Aiolfi",
        "setor": "Bucomaxilo Sobreaviso",
        "tipo_turno": "Bucomaxilo - Sobreaviso"
      },
      {
        "data": "03 abril 2026",
        "email": "",
        "horario": "07:00/07:00",
        "phone": "",
        "pos_x": 1103,
        "profissional": "Emanuel Felipe Vieira Luz",
        "setor": "Cardiologia - Sobreaviso",
        "tipo_turno": "Sobreaviso Cardiologia"
      },
      {
        "data": "03 abril 2026",
        "email": "",
        "horario": "07:00/07:00",
        "phone": "",
        "pos_x": 1440,
        "profissional": "Mateus Ceresoli Baptistella",
        "setor": "Cirurgia Geral - Sobreaviso",
        "tipo_turno": "Cirurgia Geral - Sobreaviso"
      },
      {
        "data": "03 abril 2026",
        "email": "",
        "horario": "08:00/08:00",
        "phone": "",
        "pos_x": 1777,
        "profissional": "Alberto Stolt",
        "setor": "Cirurgia Pediátrica - Sobreaviso",
        "tipo_turno": "Sobreaviso Cirurgia Pediátrica"
      },
      {
        "data": "03 abril 2026",
        "email": "",
        "horario": "08:00/08:00",
        "phone": "",
        "pos_x": 2114,
        "profissional": "Dantas Luis Lavall da Silva",
        "setor": "Cirurgia Torácica - Sobreaviso",
        "tipo_turno": "Cirurgia Torácica - Sobreaviso"
      },
      {
        "data": "03 abril 2026",
        "email": "",
        "horario": "08:00/08:00",
        "phone": "",
        "pos_x": 2451,
        "profissional": "Graciany Gasperin",
        "setor": "Cirurgia Vascular - Sobreaviso",
        "tipo_turno": "Vascular Sobreaviso"
      },
      {
        "data": "03 abril 2026",
        "email": "",
        "horario": "08:00/11:00",
        "phone": "",
        "pos_x": 2788,
        "profissional": "Eduardo Ferri Zottis",
        "setor": "Clínica Médica",
        "tipo_turno": "Rotina Clínica Médica - Matutino"
      },
      {
        "data": "03 abril 2026",
        "email": "",
        "horario": "08:00/11:00",
        "phone": "",
        "pos_x": 2788,
        "profissional": "Gabriel Vitoria Domingues",
        "setor": "Clínica Médica",
        "tipo_turno": "Rotina Clínica Médica - Matutino"
      },
      {
        "data": "03 abril 2026",
        "email": "",
        "horario": "08:00/11:00",
        "phone": "",
        "pos_x": 2788,
        "profissional": "Bianca Valandro",
        "setor": "Clínica Médica",
        "tipo_turno": "Rotina Clínica Médica - Matutino"
      },
      {
        "data": "03 abril 2026",
        "email": "",
        "horario": "08:00/11:00",
        "phone": "",
        "pos_x": 2788,
        "profissional": "Samantha de Aspiazu Damiani",
        "setor": "Clínica Médica",
        "tipo_turno": "Rotina Clínica Médica - Matutino"
      },
      {
        "data": "03 abril 2026",
        "email": "",
        "horario": "08:00/08:00",
        "phone": "",
        "pos_x": 3125,
        "profissional": "Maridiane Tormem",
        "setor": "Endoscopia - Sobreaviso",
        "tipo_turno": "Endoscopia - Sobreaviso"
      },
      {
        "data": "03 abril 2026",
        "email": "",
        "horario": "07:00/13:00",
        "phone": "",
        "pos_x": 3462,
        "profissional": "Maisa Miranda Cascaes",
        "setor": "Ginecologia e Obstetrícia - Plantão",
        "tipo_turno": "Plantão Matutino - P1"
      },
      {
        "data": "03 abril 2026",
        "email": "",
        "horario": "07:00/13:00",
        "phone": "",
        "pos_x": 3462,
        "profissional": "Morgana Filippi Chiella",
        "setor": "Ginecologia e Obstetrícia - Plantão",
        "tipo_turno": "Plantão Matutino - P2"
      },
      {
        "data": "03 abril 2026",
        "email": "",
        "horario": "07:00/07:00",
        "phone": "",
        "pos_x": 3799,
        "profissional": "Fernando Luiz de Melo Bernardi",
        "setor": "Hemodinâmica - Sobreaviso Cardiologia",
        "tipo_turno": "Hemodinâmica - Sobreaviso"
      },
      {
        "data": "03 abril 2026",
        "email": "",
        "horario": "07:00/13:00",
        "phone": "",
        "pos_x": 4136,
        "profissional": "Bruna Regina Marinho de Mello",
        "setor": "Hospitalista",
        "tipo_turno": "Hospitalista Comanejo Matutino"
      },
      {
        "data": "03 abril 2026",
        "email": "",
        "horario": "07:00/13:00",
        "phone": "",
        "pos_x": 4136,
        "profissional": "Amanda Alberici",
        "setor": "Hospitalista",
        "tipo_turno": "Hospitalista Comanejo Matutino"
      },
      {
        "data": "03 abril 2026",
        "email": "",
        "horario": "07:00/13:00",
        "phone": "",
        "pos_x": 4136,
        "profissional": "Matheus Antonio Baccin",
        "setor": "Hospitalista",
        "tipo_turno": "Hospitalista Urgência Matutino"
      },
      {
        "data": "03 abril 2026",
        "email": "",
        "horario": "06:00/14:00",
        "phone": "",
        "pos_x": 4473,
        "profissional": "Marina Oliboni Moschetta",
        "setor": "Nefrologia - Sobreaviso",
        "tipo_turno": "Matutino"
      },
      {
        "data": "03 abril 2026",
        "email": "",
        "horario": "07:00/07:00",
        "phone": "",
        "pos_x": 4810,
        "profissional": "Cezar Tarabal de Oliveira",
        "setor": "Neurocirurgia - Sobreaviso",
        "tipo_turno": "Neurocirurgia - Sobreaviso"
      },
      {
        "data": "03 abril 2026",
        "email": "",
        "horario": "07:00/07:00",
        "phone": "",
        "pos_x": 5148,
        "profissional": "Márcia Costa Morales Longhi",
        "setor": "Neurologia/U-AVC Integral - Sobreaviso",
        "tipo_turno": "Neurologia/U-AVC Integral - Sobreaviso"
      },
      {
        "data": "03 abril 2026",
        "email": "",
        "horario": "08:00/12:00",
        "phone": "",
        "pos_x": 5485,
        "profissional": "Camila Tonini",
        "setor": "Núcleo Interno de Regulação (NIR) Médico Regulador",
        "tipo_turno": "Médico - Matutino"
      },
      {
        "data": "03 abril 2026",
        "email": "",
        "horario": "07:00/07:00",
        "phone": "",
        "pos_x": 5822,
        "profissional": "Davi Machado de Souza",
        "setor": "Oftalmologia Sobreaviso",
        "tipo_turno": "Sobreaviso Oftalmologia"
      },
      {
        "data": "03 abril 2026",
        "email": "",
        "horario": "07:00/07:00",
        "phone": "",
        "pos_x": 6496,
        "profissional": "Rafael Sales de Vasconcelos Ferreira",
        "setor": "Ortopedia e Traumatologia - Sobreaviso",
        "tipo_turno": "Ortopedia  Sobreaviso - Equipe 1"
      },
      {
        "data": "03 abril 2026",
        "email": "",
        "horario": "07:00/07:00",
        "phone": "",
        "pos_x": 6496,
        "profissional": "Diego Finamor Nascimento",
        "setor": "Ortopedia e Traumatologia - Sobreaviso",
        "tipo_turno": "Ortopedia Sobreaviso  - Equipe 2"
      },
      {
        "data": "03 abril 2026",
        "email": "",
        "horario": "07:00/19:00",
        "phone": "",
        "pos_x": 6833,
        "profissional": "Maria Julia Teston",
        "setor": "Residência de Clínica Médica",
        "tipo_turno": "Res. Clínica Médica"
      },
      {
        "data": "03 abril 2026",
        "email": "",
        "horario": "07:00/19:00",
        "phone": "",
        "pos_x": 7170,
        "profissional": "Mateus Henrique Provim",
        "setor": "Residência de Cirurgia Geral",
        "tipo_turno": "DIA"
      },
      {
        "data": "03 abril 2026",
        "email": "",
        "horario": "07:00/13:00",
        "phone": "",
        "pos_x": 7507,
        "profissional": "Eliana Iora Schneider",
        "setor": "Serviço de Urgência e Emergência",
        "tipo_turno": "P1 - EMERGÊNCIA"
      },
      {
        "data": "03 abril 2026",
        "email": "",
        "horario": "07:00/13:00",
        "phone": "",
        "pos_x": 7507,
        "profissional": "Vanessa Vitoria Kerkhoff",
        "setor": "Serviço de Urgência e Emergência",
        "tipo_turno": "P2 - PRONTO ATENDIMENTO"
      },
      {
        "data": "03 abril 2026",
        "email": "",
        "horario": "09:00/18:00",
        "phone": "",
        "pos_x": 7507,
        "profissional": "Maria Luiza Hensel",
        "setor": "Serviço de Urgência e Emergência",
        "tipo_turno": "EMERGÊNCIA - LÍDER"
      },
      {
        "data": "03 abril 2026",
        "email": "",
        "horario": "09:00/18:00",
        "phone": "",
        "pos_x": 7507,
        "profissional": "Augusto Cancian",
        "setor": "Serviço de Urgência e Emergência",
        "tipo_turno": "RESIDENTE CLÍNICA MÉDICA"
      },
      {
        "data": "03 abril 2026",
        "email": "",
        "horario": "10:00/16:00",
        "phone": "",
        "pos_x": 7507,
        "profissional": "Luiza da Ros Schumacher",
        "setor": "Serviço de Urgência e Emergência",
        "tipo_turno": "P3 - REFORÇO"
      },
      {
        "data": "03 abril 2026",
        "email": "",
        "horario": "07:00/07:00",
        "phone": "",
        "pos_x": 7844,
        "profissional": "Mario Goto",
        "setor": "Transplante - Sobreaviso Cirurgia",
        "tipo_turno": "Cirurgia Geral - 1"
      },
      {
        "data": "03 abril 2026",
        "email": "",
        "horario": "07:00/07:00",
        "phone": "",
        "pos_x": 7844,
        "profissional": "Thiago Felippe Reck",
        "setor": "Transplante - Sobreaviso Cirurgia",
        "tipo_turno": "Cirurgia Geral - 2"
      },
      {
        "data": "03 abril 2026",
        "email": "",
        "horario": "07:00/07:00",
        "phone": "",
        "pos_x": 7844,
        "profissional": "Juliano Ferneda",
        "setor": "Transplante - Sobreaviso Cirurgia",
        "tipo_turno": "Urologia"
      },
      {
        "data": "03 abril 2026",
        "email": "",
        "horario": "07:00/13:00",
        "phone": "",
        "pos_x": 8518,
        "profissional": "Bruna Bassotti Favretto",
        "setor": "Unidade de Cuidados Intermediários Neonatais - UCINCo E Sala de Parto - Escala Médica",
        "tipo_turno": "Plantão - Matutino"
      },
      {
        "data": "03 abril 2026",
        "email": "",
        "horario": "07:00/13:00",
        "phone": "",
        "pos_x": 8518,
        "profissional": "Marcia de Menezes Bergamo",
        "setor": "Unidade de Cuidados Intermediários Neonatais - UCINCo E Sala de Parto - Escala Médica",
        "tipo_turno": "Rotina UCIN - Matutino"
      },
      {
        "data": "03 abril 2026",
        "email": "",
        "horario": "07:00/13:00",
        "phone": "",
        "pos_x": 8855,
        "profissional": "Hellen Katya Wiebbelling",
        "setor": "Unidade de Terapia Intensiva (UTI) Adulto I",
        "tipo_turno": "Matutino"
      },
      {
        "data": "03 abril 2026",
        "email": "",
        "horario": "09:00/15:00",
        "phone": "",
        "pos_x": 8855,
        "profissional": "Matheus De Oliveira Brock",
        "setor": "Unidade de Terapia Intensiva (UTI) Adulto I",
        "tipo_turno": "Rotina"
      },
      {
        "data": "03 abril 2026",
        "email": "",
        "horario": "07:00/13:00",
        "phone": "",
        "pos_x": 9192,
        "profissional": "Allan Douglas Santos",
        "setor": "Unidade de Terapia Intensiva (UTI) Adulto II",
        "tipo_turno": "Matutino"
      },
      {
        "data": "03 abril 2026",
        "email": "",
        "horario": "07:00/13:00",
        "phone": "",
        "pos_x": 9192,
        "profissional": "Adelaine Marilia Pinheiro",
        "setor": "Unidade de Terapia Intensiva (UTI) Adulto II",
        "tipo_turno": "Rotina"
      },
      {
        "data": "03 abril 2026",
        "email": "",
        "horario": "07:00/13:00",
        "phone": "",
        "pos_x": 9529,
        "profissional": "Emanuel Felipe Vieira Luz",
        "setor": "Unidade de Terapia Intensiva (UTI) Adulto III",
        "tipo_turno": "Matutino"
      },
      {
        "data": "03 abril 2026",
        "email": "",
        "horario": "09:00/15:00",
        "phone": "",
        "pos_x": 9529,
        "profissional": "Thiago Muniz de Lima",
        "setor": "Unidade de Terapia Intensiva (UTI) Adulto III",
        "tipo_turno": "Rotina"
      },
      {
        "data": "03 abril 2026",
        "email": "",
        "horario": "07:00/12:00",
        "phone": "",
        "pos_x": 9866,
        "profissional": "Regiany Paula Gonçalves de Oliveira Carvalho da Silva",
        "setor": "Unidade de Terapia Intensiva (UTI) Neonatal - Plantão - Escala Médica",
        "tipo_turno": "Rotina"
      },
      {
        "data": "03 abril 2026",
        "email": "",
        "horario": "07:00/13:00",
        "phone": "",
        "pos_x": 9866,
        "profissional": "Marina Emely Jorge",
        "setor": "Unidade de Terapia Intensiva (UTI) Neonatal - Plantão - Escala Médica",
        "tipo_turno": "Matutino"
      },
      {
        "data": "03 abril 2026",
        "email": "",
        "horario": "07:00/07:00",
        "phone": "",
        "pos_x": 10203,
        "profissional": "Vinicius Rubin",
        "setor": "Urologia Sobreaviso",
        "tipo_turno": "Sobreaviso Urologia"
      },
      {
        "data": "03 abril 2026",
        "email": "",
        "horario": "13:00/17:00",
        "phone": "",
        "pos_x": 429,
        "profissional": "Patricia Carla De Lima",
        "setor": "Ambulatório De Oncologia Pediátrica",
        "tipo_turno": "Ambulatório de Oncologia"
      },
      {
        "data": "03 abril 2026",
        "email": "",
        "horario": "13:00/16:00",
        "phone": "",
        "pos_x": 2788,
        "profissional": "Willian Di Domenico",
        "setor": "Clínica Médica",
        "tipo_turno": "Rotina Clínica Médica - Vespertino"
      },
      {
        "data": "03 abril 2026",
        "email": "",
        "horario": "13:00/19:00",
        "phone": "",
        "pos_x": 3462,
        "profissional": "Maisa Miranda Cascaes",
        "setor": "Ginecologia e Obstetrícia - Plantão",
        "tipo_turno": "Plantão Vespertino - P1"
      },
      {
        "data": "03 abril 2026",
        "email": "",
        "horario": "13:00/19:00",
        "phone": "",
        "pos_x": 3462,
        "profissional": "Morgana Filippi Chiella",
        "setor": "Ginecologia e Obstetrícia - Plantão",
        "tipo_turno": "Plantão Vespertino - P2"
      },
      {
        "data": "03 abril 2026",
        "email": "",
        "horario": "19:00/07:00",
        "phone": "",
        "pos_x": 3462,
        "profissional": "Shayane Luiza Rebelatto",
        "setor": "Ginecologia e Obstetrícia - Plantão",
        "tipo_turno": "Plantão Noturno - P1"
      },
      {
        "data": "03 abril 2026",
        "email": "",
        "horario": "19:00/07:00",
        "phone": "",
        "pos_x": 3462,
        "profissional": "Maisa Miranda Cascaes",
        "setor": "Ginecologia e Obstetrícia - Plantão",
        "tipo_turno": "Plantão Noturno - P1"
      },
      {
        "data": "03 abril 2026",
        "email": "",
        "horario": "13:00/19:00",
        "phone": "",
        "pos_x": 4136,
        "profissional": "Amanda Alberici",
        "setor": "Hospitalista",
        "tipo_turno": "Hospitalista Comanejo Vespertino"
      },
      {
        "data": "03 abril 2026",
        "email": "",
        "horario": "13:00/19:00",
        "phone": "",
        "pos_x": 4136,
        "profissional": "Bruno Taddeo Nogueira Alves Soares De Alvarenga",
        "setor": "Hospitalista",
        "tipo_turno": "Hospitalista Urgência Vespertino"
      },
      {
        "data": "03 abril 2026",
        "email": "",
        "horario": "19:00/07:00",
        "phone": "",
        "pos_x": 4136,
        "profissional": "Camila Tonini",
        "setor": "Hospitalista",
        "tipo_turno": "Noturno"
      },
      {
        "data": "03 abril 2026",
        "email": "",
        "horario": "14:00/06:00",
        "phone": "",
        "pos_x": 4473,
        "profissional": "Marcelo Eduardo Heinig",
        "setor": "Nefrologia - Sobreaviso",
        "tipo_turno": "Vesp - Noturno"
      },
      {
        "data": "03 abril 2026",
        "email": "",
        "horario": "13:00/17:00",
        "phone": "",
        "pos_x": 5485,
        "profissional": "Juciana Belini",
        "setor": "Núcleo Interno de Regulação (NIR) Médico Regulador",
        "tipo_turno": "Médico - Vespertino"
      },
      {
        "data": "03 abril 2026",
        "email": "",
        "horario": "17:00/19:00",
        "phone": "",
        "pos_x": 6159,
        "profissional": "Kaliandra de Almeida",
        "setor": "Oncologia Pediátrica - Sobreaviso",
        "tipo_turno": "Sobreaviso Oncologia"
      },
      {
        "data": "03 abril 2026",
        "email": "",
        "horario": "19:00/07:00",
        "phone": "",
        "pos_x": 6159,
        "profissional": "Kaliandra de Almeida",
        "setor": "Oncologia Pediátrica - Sobreaviso",
        "tipo_turno": "Sobreaviso Oncologia"
      },
      {
        "data": "03 abril 2026",
        "email": "",
        "horario": "19:00/07:00",
        "phone": "",
        "pos_x": 6833,
        "profissional": "Augusto Cancian",
        "setor": "Residência de Clínica Médica",
        "tipo_turno": "Res. Clínica Médica Noturno"
      },
      {
        "data": "03 abril 2026",
        "email": "",
        "horario": "19:00/07:00",
        "phone": "",
        "pos_x": 6833,
        "profissional": "Sofia Wanderley da Cunha Santos",
        "setor": "Residência de Clínica Médica",
        "tipo_turno": "Res. Clinica Méidica Intermediário"
      },
      {
        "data": "03 abril 2026",
        "email": "",
        "horario": "19:00/07:00",
        "phone": "",
        "pos_x": 7170,
        "profissional": "Maria Antônia Bortoli Giongo",
        "setor": "Residência de Cirurgia Geral",
        "tipo_turno": "NOITE"
      },
      {
        "data": "03 abril 2026",
        "email": "",
        "horario": "13:00/19:00",
        "phone": "",
        "pos_x": 7507,
        "profissional": "Eliana Iora Schneider",
        "setor": "Serviço de Urgência e Emergência",
        "tipo_turno": "P1 - EMERGÊNCIA"
      },
      {
        "data": "03 abril 2026",
        "email": "",
        "horario": "13:00/19:00",
        "phone": "",
        "pos_x": 7507,
        "profissional": "Maria Eduarda Wilvert",
        "setor": "Serviço de Urgência e Emergência",
        "tipo_turno": "P2 - PRONTO ATENDIMENTO"
      },
      {
        "data": "03 abril 2026",
        "email": "",
        "horario": "16:00/22:00",
        "phone": "",
        "pos_x": 7507,
        "profissional": "Naila Cerutti",
        "setor": "Serviço de Urgência e Emergência",
        "tipo_turno": "P3 - REFORÇO"
      },
      {
        "data": "03 abril 2026",
        "email": "",
        "horario": "18:00/00:00",
        "phone": "",
        "pos_x": 7507,
        "profissional": "Bruna Raquel Kessler",
        "setor": "Serviço de Urgência e Emergência",
        "tipo_turno": "P4 - REFORÇO"
      },
      {
        "data": "03 abril 2026",
        "email": "",
        "horario": "19:00/07:00",
        "phone": "",
        "pos_x": 7507,
        "profissional": "William Vinicius Weber",
        "setor": "Serviço de Urgência e Emergência",
        "tipo_turno": "P1 - EMERGÊNCIA"
      },
      {
        "data": "03 abril 2026",
        "email": "",
        "horario": "19:00/07:00",
        "phone": "",
        "pos_x": 7507,
        "profissional": "Luisa Cancian Stieler",
        "setor": "Serviço de Urgência e Emergência",
        "tipo_turno": "P2 - PRONTO ATENDIMENTO"
      },
      {
        "data": "03 abril 2026",
        "email": "",
        "horario": "18:30/07:30",
        "phone": "",
        "pos_x": 8181,
        "profissional": "João Roberto Munhoz Zorzetto",
        "setor": "Ultrassonografia - Sobreaviso",
        "tipo_turno": "Ultrassonografia - Sobreaviso"
      },
      {
        "data": "03 abril 2026",
        "email": "",
        "horario": "13:00/17:00",
        "phone": "",
        "pos_x": 8518,
        "profissional": "Marcia de Menezes Bergamo",
        "setor": "Unidade de Cuidados Intermediários Neonatais - UCINCo E Sala de Parto - Escala Médica",
        "tipo_turno": "Rotina UCIN - Vespertino"
      },
      {
        "data": "03 abril 2026",
        "email": "",
        "horario": "13:00/19:00",
        "phone": "",
        "pos_x": 8518,
        "profissional": "Bruna Bassotti Favretto",
        "setor": "Unidade de Cuidados Intermediários Neonatais - UCINCo E Sala de Parto - Escala Médica",
        "tipo_turno": "Plantão - Vespertino"
      },
      {
        "data": "03 abril 2026",
        "email": "",
        "horario": "19:00/07:00",
        "phone": "",
        "pos_x": 8518,
        "profissional": "Danielle Martins dos Santos",
        "setor": "Unidade de Cuidados Intermediários Neonatais - UCINCo E Sala de Parto - Escala Médica",
        "tipo_turno": "Plantão - Noturno"
      },
      {
        "data": "03 abril 2026",
        "email": "",
        "horario": "13:00/19:00",
        "phone": "",
        "pos_x": 8855,
        "profissional": "Hellen Katya Wiebbelling",
        "setor": "Unidade de Terapia Intensiva (UTI) Adulto I",
        "tipo_turno": "Vespertino"
      },
      {
        "data": "03 abril 2026",
        "email": "",
        "horario": "19:00/07:00",
        "phone": "",
        "pos_x": 8855,
        "profissional": "Eduardo Formoso Goldschimidt",
        "setor": "Unidade de Terapia Intensiva (UTI) Adulto I",
        "tipo_turno": "Noturno"
      },
      {
        "data": "03 abril 2026",
        "email": "",
        "horario": "13:00/19:00",
        "phone": "",
        "pos_x": 9192,
        "profissional": "Adelaine Marilia Pinheiro",
        "setor": "Unidade de Terapia Intensiva (UTI) Adulto II",
        "tipo_turno": "Vespertino"
      },
      {
        "data": "03 abril 2026",
        "email": "",
        "horario": "19:00/07:00",
        "phone": "",
        "pos_x": 9192,
        "profissional": "Michel Peruzzo",
        "setor": "Unidade de Terapia Intensiva (UTI) Adulto II",
        "tipo_turno": "Noturno"
      },
      {
        "data": "03 abril 2026",
        "email": "",
        "horario": "13:00/19:00",
        "phone": "",
        "pos_x": 9529,
        "profissional": "João Orlando Rodrigues da Silva",
        "setor": "Unidade de Terapia Intensiva (UTI) Adulto III",
        "tipo_turno": "Vespertino"
      },
      {
        "data": "03 abril 2026",
        "email": "",
        "horario": "19:00/07:00",
        "phone": "",
        "pos_x": 9529,
        "profissional": "João Orlando Rodrigues da Silva",
        "setor": "Unidade de Terapia Intensiva (UTI) Adulto III",
        "tipo_turno": "Noturno"
      },
      {
        "data": "03 abril 2026",
        "email": "",
        "horario": "13:00/19:00",
        "phone": "",
        "pos_x": 9866,
        "profissional": "Marina Emely Jorge",
        "setor": "Unidade de Terapia Intensiva (UTI) Neonatal - Plantão - Escala Médica",
        "tipo_turno": "Vespertino"
      },
      {
        "data": "03 abril 2026",
        "email": "",
        "horario": "19:00/07:00",
        "phone": "",
        "pos_x": 9866,
        "profissional": "Kaline Chiella",
        "setor": "Unidade de Terapia Intensiva (UTI) Neonatal - Plantão - Escala Médica",
        "tipo_turno": "Noturno"
      },
      {
        "data": "03 abril 2026",
        "email": "",
        "horario": "07:00/08:00",
        "phone": "",
        "pos_x": 6159,
        "profissional": "Patricia Carla De Lima",
        "setor": "Oncologia Pediátrica - Sobreaviso",
        "tipo_turno": "Sobre Aviso Oncologia"
      }
    ],
    "total": 82
  },
  "data_backup": "04/04/2026",
  "hora_backup": "10:02"
}