{
  "atual": {
    "data": "21 junho 2026",
    "data_simples": "21/06/2026",
    "registros": [
      {
        "data": "21 junho 2026",
        "email": "fernadocbuchele@gmail.com",
        "horario": "07:00/07:00",
        "phone": "(49) 98828-6262",
        "pos_x": 429,
        "profissional": "Fernando Luiz Chiella Buchele",
        "setor": "Bucomaxilo Sobreaviso",
        "tipo_turno": "Bucomaxilo - Sobreaviso"
      },
      {
        "data": "21 junho 2026",
        "email": "drathaishelou@gmail.com",
        "horario": "07:00/07:00",
        "phone": "(49) 99109-5531",
        "pos_x": 766,
        "profissional": "Thais Nascimento Helou",
        "setor": "Cardiologia - Sobreaviso",
        "tipo_turno": "Sobreaviso Cardiologia"
      },
      {
        "data": "21 junho 2026",
        "email": "jamilerosset.med@gmail.com",
        "horario": "07:00/07:00",
        "phone": "(49) 98900-6804",
        "pos_x": 1103,
        "profissional": "Jamile Rosset Mocellin",
        "setor": "Cirurgia Geral - Sobreaviso",
        "tipo_turno": "Cirurgia Geral - Sobreaviso"
      },
      {
        "data": "21 junho 2026",
        "email": "stolt@desbrava.com.br",
        "horario": "08:00/08:00",
        "phone": "(49) 99917-4239",
        "pos_x": 1440,
        "profissional": "Alberto Stolt",
        "setor": "Cirurgia Pediátrica - Sobreaviso",
        "tipo_turno": "Sobreaviso Cirurgia Pediátrica"
      },
      {
        "data": "21 junho 2026",
        "email": "rovanicamargo@gmail.com",
        "horario": "08:00/08:00",
        "phone": "(49) 99987-0636",
        "pos_x": 1777,
        "profissional": "Rovani Jose Rinaldi Camargo",
        "setor": "Cirurgia Torácica - Sobreaviso",
        "tipo_turno": "Cirurgia Torácica - Sobreaviso"
      },
      {
        "data": "21 junho 2026",
        "email": "gabriel.r@unochapeco.edu.br",
        "horario": "08:00/08:00",
        "phone": "(49) 99991-2972",
        "pos_x": 2114,
        "profissional": "Gabriel Roberto Radaelli",
        "setor": "Cirurgia Vascular - Sobreaviso",
        "tipo_turno": "Vascular Sobreaviso"
      },
      {
        "data": "21 junho 2026",
        "email": "ferscort@gmail.com",
        "horario": "08:00/08:00",
        "phone": "(54) 98152-8500",
        "pos_x": 2788,
        "profissional": "Fernanda Scortegagna Annes",
        "setor": "Endoscopia - Sobreaviso",
        "tipo_turno": "Endoscopia - Sobreaviso"
      },
      {
        "data": "21 junho 2026",
        "email": "boligoncintya@gmail.com",
        "horario": "19:00/07:00",
        "phone": "(49) 99943-5502",
        "pos_x": 3125,
        "profissional": "Cintya Boligon",
        "setor": "Ginecologia e Obstetrícia - Plantão",
        "tipo_turno": "Plantão Noturno - P1"
      },
      {
        "data": "21 junho 2026",
        "email": "macascaes@hotmail.com",
        "horario": "19:00/07:00",
        "phone": "(48) 99115-1002",
        "pos_x": 3125,
        "profissional": "Maisa Miranda Cascaes",
        "setor": "Ginecologia e Obstetrícia - Plantão",
        "tipo_turno": "Plantão Noturno - P1"
      },
      {
        "data": "21 junho 2026",
        "email": "juliobarbiero@yahoo.com.br",
        "horario": "07:00/07:00",
        "phone": "(49) 99161-0662",
        "pos_x": 3462,
        "profissional": "Julio Roberto Barbiero",
        "setor": "Hemodinâmica - Sobreaviso Cardiologia",
        "tipo_turno": "Hemodinâmica - Sobreaviso"
      },
      {
        "data": "21 junho 2026",
        "email": "biia.wolschick@hotmail.com",
        "horario": "19:00/07:00",
        "phone": "(49) 99125-5659",
        "pos_x": 3799,
        "profissional": "Bianca Soder  Wolschick",
        "setor": "Hospitalista",
        "tipo_turno": "Noturno"
      },
      {
        "data": "21 junho 2026",
        "email": "marcelo.heinig@gmail.com",
        "horario": "14:00/06:00",
        "phone": "(49) 99101-6806",
        "pos_x": 4136,
        "profissional": "Marcelo Eduardo Heinig",
        "setor": "Nefrologia - Sobreaviso",
        "tipo_turno": "Vesp - Noturno"
      },
      {
        "data": "21 junho 2026",
        "email": "drluanlucena@gmail.com",
        "horario": "07:00/07:00",
        "phone": "(11) 99878-4646",
        "pos_x": 4473,
        "profissional": "Luan Lucena",
        "setor": "Neurocirurgia - Sobreaviso",
        "tipo_turno": "Neurocirurgia - Sobreaviso"
      },
      {
        "data": "21 junho 2026",
        "email": "rafael2cordeiro@gmail.com",
        "horario": "07:00/07:00",
        "phone": "(55) 99686-0661",
        "pos_x": 4810,
        "profissional": "Rafael Cordeiro dos Santos",
        "setor": "Neurologia/U-AVC Integral - Sobreaviso",
        "tipo_turno": "Neurologia/U-AVC Integral - Sobreaviso"
      },
      {
        "data": "21 junho 2026",
        "email": "davimsouza@gmail.com",
        "horario": "07:00/07:00",
        "phone": "(49) 99163-3573",
        "pos_x": 5148,
        "profissional": "Davi Machado de Souza",
        "setor": "Oftalmologia Sobreaviso",
        "tipo_turno": "Sobreaviso Oftalmologia"
      },
      {
        "data": "21 junho 2026",
        "email": "Patricialima1407@gmail.com",
        "horario": "19:00/07:00",
        "phone": "(49) 99116-3404",
        "pos_x": 5485,
        "profissional": "Patricia Carla De Lima",
        "setor": "Oncologia Pediátrica - Sobreaviso",
        "tipo_turno": "Sobreaviso Oncologia"
      },
      {
        "data": "21 junho 2026",
        "email": "dragracielipaludo@gmail.com",
        "horario": "07:00/07:00",
        "phone": "(54) 98162-9097",
        "pos_x": 5822,
        "profissional": "Gracieli Paludo",
        "setor": "Ortopedia e Traumatologia",
        "tipo_turno": "Ortopedia  Sobreaviso - Equipe 1"
      },
      {
        "data": "21 junho 2026",
        "email": "diegonascimentomed@gmail.com",
        "horario": "07:00/07:00",
        "phone": "(54) 98118-8410",
        "pos_x": 5822,
        "profissional": "Diego Finamor Nascimento",
        "setor": "Ortopedia e Traumatologia",
        "tipo_turno": "Ortopedia Sobreaviso  - Equipe 2"
      },
      {
        "data": "21 junho 2026",
        "email": "matpiton@gmail.com",
        "horario": "19:00/07:00",
        "phone": "(46) 99122-5015",
        "pos_x": 6159,
        "profissional": "Matheus Piton",
        "setor": "Residência de Clínica Médica",
        "tipo_turno": "Res. Clínica Médica Noturno"
      },
      {
        "data": "21 junho 2026",
        "email": "sofiwanderley@gmail.com",
        "horario": "19:00/07:00",
        "phone": "(21) 96752-6943",
        "pos_x": 6159,
        "profissional": "Sofia Wanderley da Cunha Santos",
        "setor": "Residência de Clínica Médica",
        "tipo_turno": "Res. Clinica Méidica Intermediário"
      },
      {
        "data": "21 junho 2026",
        "email": "hio.piler@gmail.com",
        "horario": "19:00/07:00",
        "phone": "(32) 99921-7541",
        "pos_x": 6496,
        "profissional": "Hiolanda Gomes Piler Dornelas",
        "setor": "Residência de Cirurgia Geral",
        "tipo_turno": "NOITE"
      },
      {
        "data": "21 junho 2026",
        "email": "anapaula_grabovski@hotmail.com",
        "horario": "19:00/07:00",
        "phone": "(65) 98154-1100",
        "pos_x": 6833,
        "profissional": "Ana Paula Grabovski",
        "setor": "Residência de Ginecologia e Obstetrícia",
        "tipo_turno": "Noturno"
      },
      {
        "data": "21 junho 2026",
        "email": "j.ribas@unochapeco.edu.br",
        "horario": "19:00/07:00",
        "phone": "(49) 99816-3428",
        "pos_x": 7170,
        "profissional": "Jose Augusto Nogueira Ribas",
        "setor": "Serviço de Urgência e Emergência",
        "tipo_turno": "P1 - EMERGÊNCIA"
      },
      {
        "data": "21 junho 2026",
        "email": "brunacfgabbi@gmail.com",
        "horario": "19:00/07:00",
        "phone": "(49) 99827-4102",
        "pos_x": 7170,
        "profissional": "Bruna Carolina Fagundes Gabbi",
        "setor": "Serviço de Urgência e Emergência",
        "tipo_turno": "P2 - PRONTO ATENDIMENTO"
      },
      {
        "data": "21 junho 2026",
        "email": "mariogoto@gmail.com",
        "horario": "07:00/07:00",
        "phone": "(49) 99989-0400",
        "pos_x": 7507,
        "profissional": "Mario Goto",
        "setor": "Transplante - Sobreaviso Cirurgia",
        "tipo_turno": "Cirurgia Geral - 1"
      },
      {
        "data": "21 junho 2026",
        "email": "thiagoreck@gmail.com",
        "horario": "07:00/07:00",
        "phone": "(49) 99976-9191",
        "pos_x": 7507,
        "profissional": "Thiago Felippe Reck",
        "setor": "Transplante - Sobreaviso Cirurgia",
        "tipo_turno": "Cirurgia Geral - 2"
      },
      {
        "data": "21 junho 2026",
        "email": "julianourochapeco@gmail.com",
        "horario": "07:00/07:00",
        "phone": "(49) 99157-0907",
        "pos_x": 7507,
        "profissional": "Juliano Ferneda",
        "setor": "Transplante - Sobreaviso Cirurgia",
        "tipo_turno": "Urologia"
      },
      {
        "data": "21 junho 2026",
        "email": "vgrestelli@yahoo.com.br",
        "horario": "07:30/07:30",
        "phone": "(49) 99123-4545",
        "pos_x": 7844,
        "profissional": "Vicente Gregorio Restelli",
        "setor": "Ultrassonografia - Sobreaviso",
        "tipo_turno": "Ultrassonografia - Sobreaviso Final de Semana"
      },
      {
        "data": "21 junho 2026",
        "email": "ana.simon@unochapeco.edu.br",
        "horario": "19:00/07:00",
        "phone": "(49) 99129-1329",
        "pos_x": 8181,
        "profissional": "Ana Carolina Renz Simon",
        "setor": "Unidade de Cuidados Intermediários Neonatais - UCINCo E Sala de Parto - Escala Médica",
        "tipo_turno": "Plantão - Noturno"
      },
      {
        "data": "21 junho 2026",
        "email": "baccinmatheus@gmail.com",
        "horario": "19:00/07:00",
        "phone": "(54) 99609-6875",
        "pos_x": 8518,
        "profissional": "Matheus Antonio Baccin",
        "setor": "Unidade de Terapia Intensiva (UTI) Adulto I",
        "tipo_turno": "Noturno"
      },
      {
        "data": "21 junho 2026",
        "email": "leandrop.n@hotmail.com",
        "horario": "19:00/07:00",
        "phone": "(48) 99828-2982",
        "pos_x": 8855,
        "profissional": "Leandro Paulo do Nascimento",
        "setor": "Unidade de Terapia Intensiva (UTI) Adulto II",
        "tipo_turno": "Noturno"
      },
      {
        "data": "21 junho 2026",
        "email": "claudioneto@unochapeco.edu.br",
        "horario": "19:00/07:00",
        "phone": "(49) 99920-4895",
        "pos_x": 9192,
        "profissional": "Claudio Quinan Balestrin Neto",
        "setor": "Unidade de Terapia Intensiva (UTI) Adulto III",
        "tipo_turno": "Noturno"
      },
      {
        "data": "21 junho 2026",
        "email": "carlospinkner@hotmail.com",
        "horario": "19:00/07:00",
        "phone": "(41) 99117-0062",
        "pos_x": 9529,
        "profissional": "Carlos Pinkner",
        "setor": "Unidade de Terapia Intensiva (UTI) Neonatal - Plantão - Escala Médica",
        "tipo_turno": "Noturno"
      },
      {
        "data": "21 junho 2026",
        "email": "fernadocbuchele@gmail.com",
        "horario": "19:00/07:00",
        "phone": "(92) 98113-2728",
        "pos_x": 9866,
        "profissional": "Luiz Felipe Reis Carvalho Sordi",
        "setor": "Unidade de Terapia Intensiva (UTI) Pediátrica",
        "tipo_turno": "Plantão Noturno"
      },
      {
        "data": "21 junho 2026",
        "email": "lucas.alcir.silva@gmail.com",
        "horario": "07:00/07:00",
        "phone": "(49) 99916-5657",
        "pos_x": 10203,
        "profissional": "Lucas Alcir da Silva",
        "setor": "Urologia Sobreaviso",
        "tipo_turno": "Sobreaviso Urologia"
      },
      {
        "data": "21 junho 2026",
        "email": "marciambergamo@gmail.com",
        "horario": "08:00/13:00",
        "phone": "(49) 99977-7647",
        "pos_x": 92,
        "profissional": "Marcia de Menezes Bergamo",
        "setor": "Alojamento Conjunto",
        "tipo_turno": "Rotina - Alojamento Conjunto - Final de Semana"
      },
      {
        "data": "21 junho 2026",
        "email": "anacbeheregaray@hotmail.com",
        "horario": "08:00/14:00",
        "phone": "(51) 99996-6833",
        "pos_x": 2451,
        "profissional": "Ana Carolina Muller Beheregaray",
        "setor": "Clínica Médica",
        "tipo_turno": "Rotina Finais de Semana"
      },
      {
        "data": "21 junho 2026",
        "email": "boligoncintya@gmail.com",
        "horario": "07:00/13:00",
        "phone": "(49) 99943-5502",
        "pos_x": 3125,
        "profissional": "Cintya Boligon",
        "setor": "Ginecologia e Obstetrícia - Plantão",
        "tipo_turno": "Plantão Matutino - P1"
      },
      {
        "data": "21 junho 2026",
        "email": "macascaes@hotmail.com",
        "horario": "07:00/13:00",
        "phone": "(48) 99115-1002",
        "pos_x": 3125,
        "profissional": "Maisa Miranda Cascaes",
        "setor": "Ginecologia e Obstetrícia - Plantão",
        "tipo_turno": "Plantão Matutino - P2"
      },
      {
        "data": "21 junho 2026",
        "email": "boligoncintya@gmail.com",
        "horario": "13:00/19:00",
        "phone": "(49) 99943-5502",
        "pos_x": 3125,
        "profissional": "Cintya Boligon",
        "setor": "Ginecologia e Obstetrícia - Plantão",
        "tipo_turno": "Plantão Vespertino - P1"
      },
      {
        "data": "21 junho 2026",
        "email": "macascaes@hotmail.com",
        "horario": "13:00/19:00",
        "phone": "(48) 99115-1002",
        "pos_x": 3125,
        "profissional": "Maisa Miranda Cascaes",
        "setor": "Ginecologia e Obstetrícia - Plantão",
        "tipo_turno": "Plantão Vespertino - P2"
      },
      {
        "data": "21 junho 2026",
        "email": "amandaalberici@yahoo.com.br",
        "horario": "07:00/13:00",
        "phone": "(49) 98846-9947",
        "pos_x": 3799,
        "profissional": "Amanda Alberici",
        "setor": "Hospitalista",
        "tipo_turno": "Hospitalista Comanejo Matutino"
      },
      {
        "data": "21 junho 2026",
        "email": "brunapolettobp@hotmail.com",
        "horario": "07:00/13:00",
        "phone": "(46) 99975-0033",
        "pos_x": 3799,
        "profissional": "Bruna Poletto",
        "setor": "Hospitalista",
        "tipo_turno": "Hospitalista Urgência Matutino"
      },
      {
        "data": "21 junho 2026",
        "email": "biia.wolschick@hotmail.com",
        "horario": "13:00/19:00",
        "phone": "(49) 99125-5659",
        "pos_x": 3799,
        "profissional": "Bianca Soder  Wolschick",
        "setor": "Hospitalista",
        "tipo_turno": "Hospitalista Urgência Vespertino"
      },
      {
        "data": "21 junho 2026",
        "email": "marcelo.heinig@gmail.com",
        "horario": "06:00/14:00",
        "phone": "(49) 99101-6806",
        "pos_x": 4136,
        "profissional": "Marcelo Eduardo Heinig",
        "setor": "Nefrologia - Sobreaviso",
        "tipo_turno": "Matutino"
      },
      {
        "data": "21 junho 2026",
        "email": "Patricialima1407@gmail.com",
        "horario": "07:00/19:00",
        "phone": "(49) 99116-3404",
        "pos_x": 5485,
        "profissional": "Patricia Carla De Lima",
        "setor": "Oncologia Pediátrica - Sobreaviso",
        "tipo_turno": "Sobreaviso Oncologia"
      },
      {
        "data": "21 junho 2026",
        "email": "mariajteston@gmail.com",
        "horario": "07:00/19:00",
        "phone": "(49) 99921-5262",
        "pos_x": 6159,
        "profissional": "Maria Julia Teston",
        "setor": "Residência de Clínica Médica",
        "tipo_turno": "Res. Clínica Médica"
      },
      {
        "data": "21 junho 2026",
        "email": "natigoehr@gmail.com",
        "horario": "07:00/19:00",
        "phone": "(49) 99151-7009",
        "pos_x": 6496,
        "profissional": "Natália Cristhine Lazarin Goehr",
        "setor": "Residência de Cirurgia Geral",
        "tipo_turno": "DIA"
      },
      {
        "data": "21 junho 2026",
        "email": "nkarolrech@gmail.com",
        "horario": "07:00/13:00",
        "phone": "(49) 99835-4105",
        "pos_x": 6833,
        "profissional": "Nathália Karolina Rech",
        "setor": "Residência de Ginecologia e Obstetrícia",
        "tipo_turno": "Manhã"
      },
      {
        "data": "21 junho 2026",
        "email": "nkarolrech@gmail.com",
        "horario": "13:00/19:00",
        "phone": "(49) 99835-4105",
        "pos_x": 6833,
        "profissional": "Nathália Karolina Rech",
        "setor": "Residência de Ginecologia e Obstetrícia",
        "tipo_turno": "Tarde"
      },
      {
        "data": "21 junho 2026",
        "email": "j.ribas@unochapeco.edu.br",
        "horario": "07:00/13:00",
        "phone": "(49) 99816-3428",
        "pos_x": 7170,
        "profissional": "Jose Augusto Nogueira Ribas",
        "setor": "Serviço de Urgência e Emergência",
        "tipo_turno": "P1 - EMERGÊNCIA"
      },
      {
        "data": "21 junho 2026",
        "email": "francihoff@hotmail.com",
        "horario": "07:00/13:00",
        "phone": "(55) 98138-9719",
        "pos_x": 7170,
        "profissional": "Francine Ehrhardt Hoffmann",
        "setor": "Serviço de Urgência e Emergência",
        "tipo_turno": "P2 - PRONTO ATENDIMENTO"
      },
      {
        "data": "21 junho 2026",
        "email": "henrikegandolfi@gmail.com",
        "horario": "10:00/16:00",
        "phone": "(49) 38851-1268",
        "pos_x": 7170,
        "profissional": "Henrike Nathan Gandolfi",
        "setor": "Serviço de Urgência e Emergência",
        "tipo_turno": "P3 - REFORÇO"
      },
      {
        "data": "21 junho 2026",
        "email": "j.ribas@unochapeco.edu.br",
        "horario": "13:00/19:00",
        "phone": "(49) 99816-3428",
        "pos_x": 7170,
        "profissional": "Jose Augusto Nogueira Ribas",
        "setor": "Serviço de Urgência e Emergência",
        "tipo_turno": "P1 - EMERGÊNCIA"
      },
      {
        "data": "21 junho 2026",
        "email": "francihoff@hotmail.com",
        "horario": "13:00/19:00",
        "phone": "(55) 98138-9719",
        "pos_x": 7170,
        "profissional": "Francine Ehrhardt Hoffmann",
        "setor": "Serviço de Urgência e Emergência",
        "tipo_turno": "P2 - PRONTO ATENDIMENTO"
      },
      {
        "data": "21 junho 2026",
        "email": "marcieleznatali@gmail.com",
        "horario": "14:00/22:00",
        "phone": "(49) 98401-1736",
        "pos_x": 7170,
        "profissional": "Marciele Natali Franzosi",
        "setor": "Serviço de Urgência e Emergência",
        "tipo_turno": "P4 - REFORÇO FDS"
      },
      {
        "data": "21 junho 2026",
        "email": "letimodelski@hotmail.com",
        "horario": "16:00/22:00",
        "phone": "(54) 99615-3366",
        "pos_x": 7170,
        "profissional": "Leticia Rosa Modelski",
        "setor": "Serviço de Urgência e Emergência",
        "tipo_turno": "P3 - REFORÇO"
      },
      {
        "data": "21 junho 2026",
        "email": "marciambergamo@gmail.com",
        "horario": "07:00/08:00",
        "phone": "(49) 99977-7647",
        "pos_x": 8181,
        "profissional": "Marcia de Menezes Bergamo",
        "setor": "Unidade de Cuidados Intermediários Neonatais - UCINCo E Sala de Parto - Escala Médica",
        "tipo_turno": "Rotina UCIN - Finais de Semana Matutino"
      },
      {
        "data": "21 junho 2026",
        "email": "fernandafornari@yahoo.com.br",
        "horario": "07:00/13:00",
        "phone": "(49) 99107-9720",
        "pos_x": 8181,
        "profissional": "Fernanda Fornari",
        "setor": "Unidade de Cuidados Intermediários Neonatais - UCINCo E Sala de Parto - Escala Médica",
        "tipo_turno": "Plantão - Matutino"
      },
      {
        "data": "21 junho 2026",
        "email": "alana_romani@hotmail.com",
        "horario": "13:00/19:00",
        "phone": "(49) 98888-4554",
        "pos_x": 8181,
        "profissional": "Alana Patrícia Romani",
        "setor": "Unidade de Cuidados Intermediários Neonatais - UCINCo E Sala de Parto - Escala Médica",
        "tipo_turno": "Plantão - Vespertino"
      },
      {
        "data": "21 junho 2026",
        "email": "lisebeatriz@yahoo.com.br",
        "horario": "13:00/19:00",
        "phone": "(41) 99951-6066",
        "pos_x": 8181,
        "profissional": "Lisane Beatriz Giacomossi",
        "setor": "Unidade de Cuidados Intermediários Neonatais - UCINCo E Sala de Parto - Escala Médica",
        "tipo_turno": "Rotina UCIN - Finais de Semana"
      },
      {
        "data": "21 junho 2026",
        "email": "claudioneto@unochapeco.edu.br",
        "horario": "07:00/13:00",
        "phone": "(49) 99920-4895",
        "pos_x": 8518,
        "profissional": "Claudio Quinan Balestrin Neto",
        "setor": "Unidade de Terapia Intensiva (UTI) Adulto I",
        "tipo_turno": "Matutino"
      },
      {
        "data": "21 junho 2026",
        "email": "menegatvc@hotmail.com",
        "horario": "07:30/08:30",
        "phone": "(54) 99941-5847",
        "pos_x": 8518,
        "profissional": "Vinícius Colle Menegat",
        "setor": "Unidade de Terapia Intensiva (UTI) Adulto I",
        "tipo_turno": "Rotina Matutino - Final de Semana"
      },
      {
        "data": "21 junho 2026",
        "email": "claudioneto@unochapeco.edu.br",
        "horario": "13:00/19:00",
        "phone": "(49) 99920-4895",
        "pos_x": 8518,
        "profissional": "Claudio Quinan Balestrin Neto",
        "setor": "Unidade de Terapia Intensiva (UTI) Adulto I",
        "tipo_turno": "Vespertino"
      },
      {
        "data": "21 junho 2026",
        "email": "menegatvc@hotmail.com",
        "horario": "13:30/14:30",
        "phone": "(54) 99941-5847",
        "pos_x": 8518,
        "profissional": "Vinícius Colle Menegat",
        "setor": "Unidade de Terapia Intensiva (UTI) Adulto I",
        "tipo_turno": "Rotina Vespertino - Final de semana"
      },
      {
        "data": "21 junho 2026",
        "email": "elaineforgiarini@gmail.com",
        "horario": "07:00/13:00",
        "phone": "(55) 98141-0589",
        "pos_x": 8855,
        "profissional": "Elaine Aparecida Forgiarini",
        "setor": "Unidade de Terapia Intensiva (UTI) Adulto II",
        "tipo_turno": "Matutino"
      },
      {
        "data": "21 junho 2026",
        "email": "menegatvc@hotmail.com",
        "horario": "08:30/09:30",
        "phone": "(54) 99941-5847",
        "pos_x": 8855,
        "profissional": "Vinícius Colle Menegat",
        "setor": "Unidade de Terapia Intensiva (UTI) Adulto II",
        "tipo_turno": "Rotina Matutino - Final de Semana"
      },
      {
        "data": "21 junho 2026",
        "email": "leandrop.n@hotmail.com",
        "horario": "13:00/19:00",
        "phone": "(48) 99828-2982",
        "pos_x": 8855,
        "profissional": "Leandro Paulo do Nascimento",
        "setor": "Unidade de Terapia Intensiva (UTI) Adulto II",
        "tipo_turno": "Vespertino"
      },
      {
        "data": "21 junho 2026",
        "email": "menegatvc@hotmail.com",
        "horario": "14:30/15:30",
        "phone": "(54) 99941-5847",
        "pos_x": 8855,
        "profissional": "Vinícius Colle Menegat",
        "setor": "Unidade de Terapia Intensiva (UTI) Adulto II",
        "tipo_turno": "Rotina Vespertino- Final de Semana"
      },
      {
        "data": "21 junho 2026",
        "email": "seidlercesar@gmail.com",
        "horario": "07:00/13:00",
        "phone": "(49) 98808-0201",
        "pos_x": 9192,
        "profissional": "Cesar Augusto Seidler Junior",
        "setor": "Unidade de Terapia Intensiva (UTI) Adulto III",
        "tipo_turno": "Matutino"
      },
      {
        "data": "21 junho 2026",
        "email": "menegatvc@hotmail.com",
        "horario": "09:30/10:30",
        "phone": "(54) 99941-5847",
        "pos_x": 9192,
        "profissional": "Vinícius Colle Menegat",
        "setor": "Unidade de Terapia Intensiva (UTI) Adulto III",
        "tipo_turno": "Rotina Matutino - Final de Semana"
      },
      {
        "data": "21 junho 2026",
        "email": "seidlercesar@gmail.com",
        "horario": "13:00/19:00",
        "phone": "(49) 98808-0201",
        "pos_x": 9192,
        "profissional": "Cesar Augusto Seidler Junior",
        "setor": "Unidade de Terapia Intensiva (UTI) Adulto III",
        "tipo_turno": "Vespertino"
      },
      {
        "data": "21 junho 2026",
        "email": "menegatvc@hotmail.com",
        "horario": "15:30/16:30",
        "phone": "(54) 99941-5847",
        "pos_x": 9192,
        "profissional": "Vinícius Colle Menegat",
        "setor": "Unidade de Terapia Intensiva (UTI) Adulto III",
        "tipo_turno": "Rotina Vespertino - Final de Semana"
      },
      {
        "data": "21 junho 2026",
        "email": "lisebeatriz@yahoo.com.br",
        "horario": "07:00/12:00",
        "phone": "(41) 99951-6066",
        "pos_x": 9529,
        "profissional": "Lisane Beatriz Giacomossi",
        "setor": "Unidade de Terapia Intensiva (UTI) Neonatal - Plantão - Escala Médica",
        "tipo_turno": "Rotina"
      },
      {
        "data": "21 junho 2026",
        "email": "carlospinkner@hotmail.com",
        "horario": "07:00/13:00",
        "phone": "(41) 99117-0062",
        "pos_x": 9529,
        "profissional": "Carlos Pinkner",
        "setor": "Unidade de Terapia Intensiva (UTI) Neonatal - Plantão - Escala Médica",
        "tipo_turno": "Matutino"
      },
      {
        "data": "21 junho 2026",
        "email": "carlospinkner@hotmail.com",
        "horario": "13:00/19:00",
        "phone": "(41) 99117-0062",
        "pos_x": 9529,
        "profissional": "Carlos Pinkner",
        "setor": "Unidade de Terapia Intensiva (UTI) Neonatal - Plantão - Escala Médica",
        "tipo_turno": "Vespertino"
      },
      {
        "data": "21 junho 2026",
        "email": "fernandakamei@gmail.com",
        "horario": "07:00/13:00",
        "phone": "(92) 98113-2728",
        "pos_x": 9866,
        "profissional": "Luiz Felipe Reis Carvalho Sordi",
        "setor": "Unidade de Terapia Intensiva (UTI) Pediátrica",
        "tipo_turno": "Plantão Matutino"
      },
      {
        "data": "21 junho 2026",
        "email": "fernandakamei@gmail.com",
        "horario": "08:00/12:00",
        "phone": "(27) 98120-0880",
        "pos_x": 9866,
        "profissional": "Fernanda Marcenes Kamei",
        "setor": "Unidade de Terapia Intensiva (UTI) Pediátrica",
        "tipo_turno": "Médico Rotineiro I"
      },
      {
        "data": "21 junho 2026",
        "email": "fernandakamei@gmail.com",
        "horario": "13:00/19:00",
        "phone": "(92) 98113-2728",
        "pos_x": 9866,
        "profissional": "Luiz Felipe Reis Carvalho Sordi",
        "setor": "Unidade de Terapia Intensiva (UTI) Pediátrica",
        "tipo_turno": "Plantão Vespertino"
      }
    ],
    "total": 79
  },
  "anterior": {
    "data": "20 junho 2026",
    "data_simples": "20/06/2026",
    "registros": [
      {
        "data": "20 junho 2026",
        "email": "fernadocbuchele@gmail.com",
        "horario": "07:00/07:00",
        "phone": "(49) 98828-6262",
        "pos_x": 429,
        "profissional": "Fernando Luiz Chiella Buchele",
        "setor": "Bucomaxilo Sobreaviso",
        "tipo_turno": "Bucomaxilo - Sobreaviso"
      },
      {
        "data": "20 junho 2026",
        "email": "drathaishelou@gmail.com",
        "horario": "07:00/07:00",
        "phone": "(49) 99109-5531",
        "pos_x": 766,
        "profissional": "Thais Nascimento Helou",
        "setor": "Cardiologia - Sobreaviso",
        "tipo_turno": "Sobreaviso Cardiologia"
      },
      {
        "data": "20 junho 2026",
        "email": "jamilerosset.med@gmail.com",
        "horario": "07:00/07:00",
        "phone": "(49) 98900-6804",
        "pos_x": 1103,
        "profissional": "Jamile Rosset Mocellin",
        "setor": "Cirurgia Geral - Sobreaviso",
        "tipo_turno": "Cirurgia Geral - Sobreaviso"
      },
      {
        "data": "20 junho 2026",
        "email": "stolt@desbrava.com.br",
        "horario": "08:00/08:00",
        "phone": "(49) 99917-4239",
        "pos_x": 1440,
        "profissional": "Alberto Stolt",
        "setor": "Cirurgia Pediátrica - Sobreaviso",
        "tipo_turno": "Sobreaviso Cirurgia Pediátrica"
      },
      {
        "data": "20 junho 2026",
        "email": "drrodrigosr121179@gmail.com",
        "horario": "08:00/08:00",
        "phone": "(49) 99156-1330",
        "pos_x": 1777,
        "profissional": "Rodrigo  Sponchiado Rocha",
        "setor": "Cirurgia Torácica - Sobreaviso",
        "tipo_turno": "Cirurgia Torácica - Sobreaviso"
      },
      {
        "data": "20 junho 2026",
        "email": "gabriel.r@unochapeco.edu.br",
        "horario": "08:00/08:00",
        "phone": "(49) 99991-2972",
        "pos_x": 2114,
        "profissional": "Gabriel Roberto Radaelli",
        "setor": "Cirurgia Vascular - Sobreaviso",
        "tipo_turno": "Vascular Sobreaviso"
      },
      {
        "data": "20 junho 2026",
        "email": "ferscort@gmail.com",
        "horario": "08:00/08:00",
        "phone": "(54) 98152-8500",
        "pos_x": 2788,
        "profissional": "Fernanda Scortegagna Annes",
        "setor": "Endoscopia - Sobreaviso",
        "tipo_turno": "Endoscopia - Sobreaviso"
      },
      {
        "data": "20 junho 2026",
        "email": "marcus_trassi@hotmail.com",
        "horario": "19:00/07:00",
        "phone": "(48) 99696-6169",
        "pos_x": 3125,
        "profissional": "Marcus Vinicius Trassi Neves",
        "setor": "Ginecologia e Obstetrícia - Plantão",
        "tipo_turno": "Plantão Noturno - P1"
      },
      {
        "data": "20 junho 2026",
        "email": "fercm@unochapeco.edu.br",
        "horario": "19:00/07:00",
        "phone": "(49) 99902-9999",
        "pos_x": 3125,
        "profissional": "Fernanda Canello Modesti",
        "setor": "Ginecologia e Obstetrícia - Plantão",
        "tipo_turno": "Plantão Noturno - P1"
      },
      {
        "data": "20 junho 2026",
        "email": "juliobarbiero@yahoo.com.br",
        "horario": "07:00/07:00",
        "phone": "(49) 99161-0662",
        "pos_x": 3462,
        "profissional": "Julio Roberto Barbiero",
        "setor": "Hemodinâmica - Sobreaviso Cardiologia",
        "tipo_turno": "Hemodinâmica - Sobreaviso"
      },
      {
        "data": "20 junho 2026",
        "email": "biia.wolschick@hotmail.com",
        "horario": "19:00/07:00",
        "phone": "(49) 99125-5659",
        "pos_x": 3799,
        "profissional": "Bianca Soder  Wolschick",
        "setor": "Hospitalista",
        "tipo_turno": "Noturno"
      },
      {
        "data": "20 junho 2026",
        "email": "marcelo.heinig@gmail.com",
        "horario": "14:00/06:00",
        "phone": "(49) 99101-6806",
        "pos_x": 4136,
        "profissional": "Marcelo Eduardo Heinig",
        "setor": "Nefrologia - Sobreaviso",
        "tipo_turno": "Vesp - Noturno"
      },
      {
        "data": "20 junho 2026",
        "email": "drluanlucena@gmail.com",
        "horario": "07:00/07:00",
        "phone": "(11) 99878-4646",
        "pos_x": 4473,
        "profissional": "Luan Lucena",
        "setor": "Neurocirurgia - Sobreaviso",
        "tipo_turno": "Neurocirurgia - Sobreaviso"
      },
      {
        "data": "20 junho 2026",
        "email": "rafael2cordeiro@gmail.com",
        "horario": "07:00/07:00",
        "phone": "(55) 99686-0661",
        "pos_x": 4810,
        "profissional": "Rafael Cordeiro dos Santos",
        "setor": "Neurologia/U-AVC Integral - Sobreaviso",
        "tipo_turno": "Neurologia/U-AVC Integral - Sobreaviso"
      },
      {
        "data": "20 junho 2026",
        "email": "sergiosiepko@gmail.com",
        "horario": "07:00/07:00",
        "phone": "(49) 99987-6865",
        "pos_x": 5148,
        "profissional": "Sergio Francisco Siepko Junior",
        "setor": "Oftalmologia Sobreaviso",
        "tipo_turno": "Sobreaviso Oftalmologia"
      },
      {
        "data": "20 junho 2026",
        "email": "Patricialima1407@gmail.com",
        "horario": "19:00/07:00",
        "phone": "(49) 99116-3404",
        "pos_x": 5485,
        "profissional": "Patricia Carla De Lima",
        "setor": "Oncologia Pediátrica - Sobreaviso",
        "tipo_turno": "Sobreaviso Oncologia"
      },
      {
        "data": "20 junho 2026",
        "email": "dragracielipaludo@gmail.com",
        "horario": "07:00/07:00",
        "phone": "(54) 98162-9097",
        "pos_x": 5822,
        "profissional": "Gracieli Paludo",
        "setor": "Ortopedia e Traumatologia",
        "tipo_turno": "Ortopedia  Sobreaviso - Equipe 1"
      },
      {
        "data": "20 junho 2026",
        "email": "diegonascimentomed@gmail.com",
        "horario": "07:00/07:00",
        "phone": "(54) 98118-8410",
        "pos_x": 5822,
        "profissional": "Diego Finamor Nascimento",
        "setor": "Ortopedia e Traumatologia",
        "tipo_turno": "Ortopedia Sobreaviso  - Equipe 2"
      },
      {
        "data": "20 junho 2026",
        "email": "mariajteston@gmail.com",
        "horario": "19:00/07:00",
        "phone": "(49) 99921-5262",
        "pos_x": 6159,
        "profissional": "Maria Julia Teston",
        "setor": "Residência de Clínica Médica",
        "tipo_turno": "Res. Clínica Médica Noturno"
      },
      {
        "data": "20 junho 2026",
        "email": "feh_zancan@hotmail.com",
        "horario": "19:00/07:00",
        "phone": "(49) 99126-9684",
        "pos_x": 6159,
        "profissional": "Fernanda Trevisan Zancan",
        "setor": "Residência de Clínica Médica",
        "tipo_turno": "Res. Clinica Méidica Intermediário"
      },
      {
        "data": "20 junho 2026",
        "email": "pedroveiga01@hotmail.com",
        "horario": "19:00/07:00",
        "phone": "(55) 99601-3842",
        "pos_x": 6496,
        "profissional": "Pedro Leonel Fucks da Veiga",
        "setor": "Residência de Cirurgia Geral",
        "tipo_turno": "NOITE"
      },
      {
        "data": "20 junho 2026",
        "email": "lautolotti@gmail.com",
        "horario": "19:00/07:00",
        "phone": "(49) 98828-6262",
        "pos_x": 6833,
        "profissional": "Laura Tolotti",
        "setor": "Residência de Ginecologia e Obstetrícia",
        "tipo_turno": "Noturno"
      },
      {
        "data": "20 junho 2026",
        "email": "joaohperes@gmail.com",
        "horario": "19:00/07:00",
        "phone": "(49) 99835-1563",
        "pos_x": 7170,
        "profissional": "João Henrique Peres",
        "setor": "Serviço de Urgência e Emergência",
        "tipo_turno": "P1 - EMERGÊNCIA"
      },
      {
        "data": "20 junho 2026",
        "email": "lavinialuiza2002@gmail.com",
        "horario": "19:00/07:00",
        "phone": "(49) 98850-0307",
        "pos_x": 7170,
        "profissional": "Lavinia Luiza Grando",
        "setor": "Serviço de Urgência e Emergência",
        "tipo_turno": "P2 - PRONTO ATENDIMENTO"
      },
      {
        "data": "20 junho 2026",
        "email": "mariogoto@gmail.com",
        "horario": "07:00/07:00",
        "phone": "(49) 99989-0400",
        "pos_x": 7507,
        "profissional": "Mario Goto",
        "setor": "Transplante - Sobreaviso Cirurgia",
        "tipo_turno": "Cirurgia Geral - 1"
      },
      {
        "data": "20 junho 2026",
        "email": "thiagoreck@gmail.com",
        "horario": "07:00/07:00",
        "phone": "(49) 99976-9191",
        "pos_x": 7507,
        "profissional": "Thiago Felippe Reck",
        "setor": "Transplante - Sobreaviso Cirurgia",
        "tipo_turno": "Cirurgia Geral - 2"
      },
      {
        "data": "20 junho 2026",
        "email": "julianourochapeco@gmail.com",
        "horario": "07:00/07:00",
        "phone": "(49) 99157-0907",
        "pos_x": 7507,
        "profissional": "Juliano Ferneda",
        "setor": "Transplante - Sobreaviso Cirurgia",
        "tipo_turno": "Urologia"
      },
      {
        "data": "20 junho 2026",
        "email": "vgrestelli@yahoo.com.br",
        "horario": "07:30/07:30",
        "phone": "(49) 99123-4545",
        "pos_x": 7844,
        "profissional": "Vicente Gregorio Restelli",
        "setor": "Ultrassonografia - Sobreaviso",
        "tipo_turno": "Ultrassonografia - Sobreaviso Final de Semana"
      },
      {
        "data": "20 junho 2026",
        "email": "fernandafornari@yahoo.com.br",
        "horario": "19:00/07:00",
        "phone": "(49) 99107-9720",
        "pos_x": 8181,
        "profissional": "Fernanda Fornari",
        "setor": "Unidade de Cuidados Intermediários Neonatais - UCINCo E Sala de Parto - Escala Médica",
        "tipo_turno": "Plantão - Noturno"
      },
      {
        "data": "20 junho 2026",
        "email": "Samantha.aspiazu@gmail.com",
        "horario": "19:00/07:00",
        "phone": "(54) 99982-3380",
        "pos_x": 8518,
        "profissional": "Samantha de Aspiazu Damiani",
        "setor": "Unidade de Terapia Intensiva (UTI) Adulto I",
        "tipo_turno": "Noturno"
      },
      {
        "data": "20 junho 2026",
        "email": "elaineforgiarini@gmail.com",
        "horario": "19:00/07:00",
        "phone": "(55) 98141-0589",
        "pos_x": 8855,
        "profissional": "Elaine Aparecida Forgiarini",
        "setor": "Unidade de Terapia Intensiva (UTI) Adulto II",
        "tipo_turno": "Noturno"
      },
      {
        "data": "20 junho 2026",
        "email": "claudioneto@unochapeco.edu.br",
        "horario": "19:00/07:00",
        "phone": "(49) 99920-4895",
        "pos_x": 9192,
        "profissional": "Claudio Quinan Balestrin Neto",
        "setor": "Unidade de Terapia Intensiva (UTI) Adulto III",
        "tipo_turno": "Noturno"
      },
      {
        "data": "20 junho 2026",
        "email": "fernadocbuchele@gmail.com",
        "horario": "19:00/07:00",
        "phone": "(49) 99917-5310",
        "pos_x": 9529,
        "profissional": "Fabiele Bandeira",
        "setor": "Unidade de Terapia Intensiva (UTI) Neonatal - Plantão - Escala Médica",
        "tipo_turno": "Noturno"
      },
      {
        "data": "20 junho 2026",
        "email": "fernandakamei@gmail.com",
        "horario": "19:00/07:00",
        "phone": "(27) 98120-0880",
        "pos_x": 9866,
        "profissional": "Fernanda Marcenes Kamei",
        "setor": "Unidade de Terapia Intensiva (UTI) Pediátrica",
        "tipo_turno": "Plantão Noturno"
      },
      {
        "data": "20 junho 2026",
        "email": "lucas.alcir.silva@gmail.com",
        "horario": "07:00/07:00",
        "phone": "(49) 99916-5657",
        "pos_x": 10203,
        "profissional": "Lucas Alcir da Silva",
        "setor": "Urologia Sobreaviso",
        "tipo_turno": "Sobreaviso Urologia"
      },
      {
        "data": "20 junho 2026",
        "email": "marciambergamo@gmail.com",
        "horario": "08:00/13:00",
        "phone": "(49) 99977-7647",
        "pos_x": 92,
        "profissional": "Marcia de Menezes Bergamo",
        "setor": "Alojamento Conjunto",
        "tipo_turno": "Rotina - Alojamento Conjunto - Final de Semana"
      },
      {
        "data": "20 junho 2026",
        "email": "bianca.geriatra@gmail.com",
        "horario": "08:00/14:00",
        "phone": "(54) 98103-8771",
        "pos_x": 2451,
        "profissional": "Bianca Valandro",
        "setor": "Clínica Médica",
        "tipo_turno": "Rotina Finais de Semana"
      },
      {
        "data": "20 junho 2026",
        "email": "fercm@unochapeco.edu.br",
        "horario": "07:00/13:00",
        "phone": "(49) 99902-9999",
        "pos_x": 3125,
        "profissional": "Fernanda Canello Modesti",
        "setor": "Ginecologia e Obstetrícia - Plantão",
        "tipo_turno": "Plantão Matutino - P1"
      },
      {
        "data": "20 junho 2026",
        "email": "lais.paganella@hotmail.com",
        "horario": "07:00/13:00",
        "phone": "(51) 99559-2599",
        "pos_x": 3125,
        "profissional": "Lais Paganella de Aquino",
        "setor": "Ginecologia e Obstetrícia - Plantão",
        "tipo_turno": "Plantão Matutino - P2"
      },
      {
        "data": "20 junho 2026",
        "email": "fercm@unochapeco.edu.br",
        "horario": "13:00/19:00",
        "phone": "(49) 99902-9999",
        "pos_x": 3125,
        "profissional": "Fernanda Canello Modesti",
        "setor": "Ginecologia e Obstetrícia - Plantão",
        "tipo_turno": "Plantão Vespertino - P1"
      },
      {
        "data": "20 junho 2026",
        "email": "lais.paganella@hotmail.com",
        "horario": "13:00/19:00",
        "phone": "(51) 99559-2599",
        "pos_x": 3125,
        "profissional": "Lais Paganella de Aquino",
        "setor": "Ginecologia e Obstetrícia - Plantão",
        "tipo_turno": "Plantão Vespertino - P2"
      },
      {
        "data": "20 junho 2026",
        "email": "amandaalberici@yahoo.com.br",
        "horario": "07:00/13:00",
        "phone": "(49) 98846-9947",
        "pos_x": 3799,
        "profissional": "Amanda Alberici",
        "setor": "Hospitalista",
        "tipo_turno": "Hospitalista Comanejo Matutino"
      },
      {
        "data": "20 junho 2026",
        "email": "brunapolettobp@hotmail.com",
        "horario": "07:00/13:00",
        "phone": "(46) 99975-0033",
        "pos_x": 3799,
        "profissional": "Bruna Poletto",
        "setor": "Hospitalista",
        "tipo_turno": "Hospitalista Urgência Matutino"
      },
      {
        "data": "20 junho 2026",
        "email": "brunapolettobp@hotmail.com",
        "horario": "13:00/19:00",
        "phone": "(46) 99975-0033",
        "pos_x": 3799,
        "profissional": "Bruna Poletto",
        "setor": "Hospitalista",
        "tipo_turno": "Hospitalista Urgência Vespertino"
      },
      {
        "data": "20 junho 2026",
        "email": "cristianemezzalira@hotmail.com",
        "horario": "06:00/14:00",
        "phone": "(49) 99107-0000",
        "pos_x": 4136,
        "profissional": "Geraldo Antunes Cordova",
        "setor": "Nefrologia - Sobreaviso",
        "tipo_turno": "Matutino"
      },
      {
        "data": "20 junho 2026",
        "email": "Patricialima1407@gmail.com",
        "horario": "07:00/19:00",
        "phone": "(49) 99116-3404",
        "pos_x": 5485,
        "profissional": "Patricia Carla De Lima",
        "setor": "Oncologia Pediátrica - Sobreaviso",
        "tipo_turno": "Sobreaviso Oncologia"
      },
      {
        "data": "20 junho 2026",
        "email": "ligia.oro@unochapeco.edu.br",
        "horario": "07:00/19:00",
        "phone": "(49) 99920-5947",
        "pos_x": 6159,
        "profissional": "Ligia Oro",
        "setor": "Residência de Clínica Médica",
        "tipo_turno": "Res. Clínica Médica"
      },
      {
        "data": "20 junho 2026",
        "email": "nauradanielimarcon@gmail.com",
        "horario": "07:00/19:00",
        "phone": "(54) 99971-7583",
        "pos_x": 6496,
        "profissional": "Naura Danieli Marcon",
        "setor": "Residência de Cirurgia Geral",
        "tipo_turno": "DIA"
      },
      {
        "data": "20 junho 2026",
        "email": "adriana.miyake@hotmail.com",
        "horario": "07:00/13:00",
        "phone": "(38) 99142-9975",
        "pos_x": 6833,
        "profissional": "Miyake Adriana Souza Cirqueira",
        "setor": "Residência de Ginecologia e Obstetrícia",
        "tipo_turno": "Manhã"
      },
      {
        "data": "20 junho 2026",
        "email": "lautolotti@gmail.com",
        "horario": "07:00/13:00",
        "phone": "(38) 99142-9975",
        "pos_x": 6833,
        "profissional": "Laura Tolotti",
        "setor": "Residência de Ginecologia e Obstetrícia",
        "tipo_turno": "Manhã"
      },
      {
        "data": "20 junho 2026",
        "email": "lautolotti@gmail.com",
        "horario": "13:00/19:00",
        "phone": "(38) 99142-9975",
        "pos_x": 6833,
        "profissional": "Laura Tolotti",
        "setor": "Residência de Ginecologia e Obstetrícia",
        "tipo_turno": "Tarde"
      },
      {
        "data": "20 junho 2026",
        "email": "adriana.miyake@hotmail.com",
        "horario": "13:00/19:00",
        "phone": "(38) 99142-9975",
        "pos_x": 6833,
        "profissional": "Miyake Adriana Souza Cirqueira",
        "setor": "Residência de Ginecologia e Obstetrícia",
        "tipo_turno": "Tarde"
      },
      {
        "data": "20 junho 2026",
        "email": "priscila.domingos95@gmail.com",
        "horario": "07:00/13:00",
        "phone": "(49) 99142-4137",
        "pos_x": 7170,
        "profissional": "Priscila Domingos",
        "setor": "Serviço de Urgência e Emergência",
        "tipo_turno": "P1 - EMERGÊNCIA"
      },
      {
        "data": "20 junho 2026",
        "email": "eloisa.chiella@unochapeco.edu.br",
        "horario": "07:00/13:00",
        "phone": "(49) 98817-2147",
        "pos_x": 7170,
        "profissional": "Eloisa Lehr Filippi Chiella",
        "setor": "Serviço de Urgência e Emergência",
        "tipo_turno": "P2 - PRONTO ATENDIMENTO"
      },
      {
        "data": "20 junho 2026",
        "email": "letimodelski@hotmail.com",
        "horario": "10:00/16:00",
        "phone": "(54) 99615-3366",
        "pos_x": 7170,
        "profissional": "Leticia Rosa Modelski",
        "setor": "Serviço de Urgência e Emergência",
        "tipo_turno": "P3 - REFORÇO"
      },
      {
        "data": "20 junho 2026",
        "email": "priscila.domingos95@gmail.com",
        "horario": "13:00/19:00",
        "phone": "(49) 99142-4137",
        "pos_x": 7170,
        "profissional": "Priscila Domingos",
        "setor": "Serviço de Urgência e Emergência",
        "tipo_turno": "P1 - EMERGÊNCIA"
      },
      {
        "data": "20 junho 2026",
        "email": "eloisa.chiella@unochapeco.edu.br",
        "horario": "13:00/19:00",
        "phone": "(49) 98817-2147",
        "pos_x": 7170,
        "profissional": "Eloisa Lehr Filippi Chiella",
        "setor": "Serviço de Urgência e Emergência",
        "tipo_turno": "P2 - PRONTO ATENDIMENTO"
      },
      {
        "data": "20 junho 2026",
        "email": "francihoff@hotmail.com",
        "horario": "14:00/22:00",
        "phone": "(55) 98138-9719",
        "pos_x": 7170,
        "profissional": "Francine Ehrhardt Hoffmann",
        "setor": "Serviço de Urgência e Emergência",
        "tipo_turno": "P4 - REFORÇO FDS"
      },
      {
        "data": "20 junho 2026",
        "email": "erikalbiasoli@gmail.com",
        "horario": "16:00/22:00",
        "phone": "(49) 99936-9649",
        "pos_x": 7170,
        "profissional": "Erika Luiza Biasoli",
        "setor": "Serviço de Urgência e Emergência",
        "tipo_turno": "P3 - REFORÇO"
      },
      {
        "data": "20 junho 2026",
        "email": "marciambergamo@gmail.com",
        "horario": "07:00/08:00",
        "phone": "(49) 99977-7647",
        "pos_x": 8181,
        "profissional": "Marcia de Menezes Bergamo",
        "setor": "Unidade de Cuidados Intermediários Neonatais - UCINCo E Sala de Parto - Escala Médica",
        "tipo_turno": "Rotina UCIN - Finais de Semana Matutino"
      },
      {
        "data": "20 junho 2026",
        "email": "kassiacarolinadelima@gmail.com",
        "horario": "07:00/13:00",
        "phone": "(49) 99927-0156",
        "pos_x": 8181,
        "profissional": "Kássia Carolina de Lima",
        "setor": "Unidade de Cuidados Intermediários Neonatais - UCINCo E Sala de Parto - Escala Médica",
        "tipo_turno": "Plantão - Matutino"
      },
      {
        "data": "20 junho 2026",
        "email": "kassiacarolinadelima@gmail.com",
        "horario": "13:00/19:00",
        "phone": "(49) 99927-0156",
        "pos_x": 8181,
        "profissional": "Kássia Carolina de Lima",
        "setor": "Unidade de Cuidados Intermediários Neonatais - UCINCo E Sala de Parto - Escala Médica",
        "tipo_turno": "Plantão - Vespertino"
      },
      {
        "data": "20 junho 2026",
        "email": "lisebeatriz@yahoo.com.br",
        "horario": "13:00/19:00",
        "phone": "(41) 99951-6066",
        "pos_x": 8181,
        "profissional": "Lisane Beatriz Giacomossi",
        "setor": "Unidade de Cuidados Intermediários Neonatais - UCINCo E Sala de Parto - Escala Médica",
        "tipo_turno": "Rotina UCIN - Finais de Semana"
      },
      {
        "data": "20 junho 2026",
        "email": "Samantha.aspiazu@gmail.com",
        "horario": "07:00/13:00",
        "phone": "(54) 99982-3380",
        "pos_x": 8518,
        "profissional": "Samantha de Aspiazu Damiani",
        "setor": "Unidade de Terapia Intensiva (UTI) Adulto I",
        "tipo_turno": "Matutino"
      },
      {
        "data": "20 junho 2026",
        "email": "menegatvc@hotmail.com",
        "horario": "07:30/08:30",
        "phone": "(54) 99941-5847",
        "pos_x": 8518,
        "profissional": "Vinícius Colle Menegat",
        "setor": "Unidade de Terapia Intensiva (UTI) Adulto I",
        "tipo_turno": "Rotina Matutino - Final de Semana"
      },
      {
        "data": "20 junho 2026",
        "email": "Samantha.aspiazu@gmail.com",
        "horario": "13:00/19:00",
        "phone": "(54) 99982-3380",
        "pos_x": 8518,
        "profissional": "Samantha de Aspiazu Damiani",
        "setor": "Unidade de Terapia Intensiva (UTI) Adulto I",
        "tipo_turno": "Vespertino"
      },
      {
        "data": "20 junho 2026",
        "email": "menegatvc@hotmail.com",
        "horario": "13:30/14:30",
        "phone": "(54) 99941-5847",
        "pos_x": 8518,
        "profissional": "Vinícius Colle Menegat",
        "setor": "Unidade de Terapia Intensiva (UTI) Adulto I",
        "tipo_turno": "Rotina Vespertino - Final de semana"
      },
      {
        "data": "20 junho 2026",
        "email": "baccinmatheus@gmail.com",
        "horario": "07:00/13:00",
        "phone": "(54) 99609-6875",
        "pos_x": 8855,
        "profissional": "Matheus Antonio Baccin",
        "setor": "Unidade de Terapia Intensiva (UTI) Adulto II",
        "tipo_turno": "Matutino"
      },
      {
        "data": "20 junho 2026",
        "email": "menegatvc@hotmail.com",
        "horario": "08:30/09:30",
        "phone": "(54) 99941-5847",
        "pos_x": 8855,
        "profissional": "Vinícius Colle Menegat",
        "setor": "Unidade de Terapia Intensiva (UTI) Adulto II",
        "tipo_turno": "Rotina Matutino - Final de Semana"
      },
      {
        "data": "20 junho 2026",
        "email": "baccinmatheus@gmail.com",
        "horario": "13:00/19:00",
        "phone": "(54) 99609-6875",
        "pos_x": 8855,
        "profissional": "Matheus Antonio Baccin",
        "setor": "Unidade de Terapia Intensiva (UTI) Adulto II",
        "tipo_turno": "Vespertino"
      },
      {
        "data": "20 junho 2026",
        "email": "menegatvc@hotmail.com",
        "horario": "14:30/15:30",
        "phone": "(54) 99941-5847",
        "pos_x": 8855,
        "profissional": "Vinícius Colle Menegat",
        "setor": "Unidade de Terapia Intensiva (UTI) Adulto II",
        "tipo_turno": "Rotina Vespertino- Final de Semana"
      },
      {
        "data": "20 junho 2026",
        "email": "leandrop.n@hotmail.com",
        "horario": "07:00/13:00",
        "phone": "(48) 99828-2982",
        "pos_x": 9192,
        "profissional": "Leandro Paulo do Nascimento",
        "setor": "Unidade de Terapia Intensiva (UTI) Adulto III",
        "tipo_turno": "Matutino"
      },
      {
        "data": "20 junho 2026",
        "email": "menegatvc@hotmail.com",
        "horario": "09:30/10:30",
        "phone": "(54) 99941-5847",
        "pos_x": 9192,
        "profissional": "Vinícius Colle Menegat",
        "setor": "Unidade de Terapia Intensiva (UTI) Adulto III",
        "tipo_turno": "Rotina Matutino - Final de Semana"
      },
      {
        "data": "20 junho 2026",
        "email": "leandrop.n@hotmail.com",
        "horario": "13:00/19:00",
        "phone": "(48) 99828-2982",
        "pos_x": 9192,
        "profissional": "Leandro Paulo do Nascimento",
        "setor": "Unidade de Terapia Intensiva (UTI) Adulto III",
        "tipo_turno": "Vespertino"
      },
      {
        "data": "20 junho 2026",
        "email": "menegatvc@hotmail.com",
        "horario": "15:30/16:30",
        "phone": "(54) 99941-5847",
        "pos_x": 9192,
        "profissional": "Vinícius Colle Menegat",
        "setor": "Unidade de Terapia Intensiva (UTI) Adulto III",
        "tipo_turno": "Rotina Vespertino - Final de Semana"
      },
      {
        "data": "20 junho 2026",
        "email": "lisebeatriz@yahoo.com.br",
        "horario": "07:00/12:00",
        "phone": "(41) 99951-6066",
        "pos_x": 9529,
        "profissional": "Lisane Beatriz Giacomossi",
        "setor": "Unidade de Terapia Intensiva (UTI) Neonatal - Plantão - Escala Médica",
        "tipo_turno": "Rotina"
      },
      {
        "data": "20 junho 2026",
        "email": "carlospinkner@hotmail.com",
        "horario": "07:00/13:00",
        "phone": "(41) 99117-0062",
        "pos_x": 9529,
        "profissional": "Carlos Pinkner",
        "setor": "Unidade de Terapia Intensiva (UTI) Neonatal - Plantão - Escala Médica",
        "tipo_turno": "Matutino"
      },
      {
        "data": "20 junho 2026",
        "email": "carlospinkner@hotmail.com",
        "horario": "13:00/19:00",
        "phone": "(41) 99117-0062",
        "pos_x": 9529,
        "profissional": "Carlos Pinkner",
        "setor": "Unidade de Terapia Intensiva (UTI) Neonatal - Plantão - Escala Médica",
        "tipo_turno": "Vespertino"
      },
      {
        "data": "20 junho 2026",
        "email": "fernandakamei@gmail.com",
        "horario": "07:00/13:00",
        "phone": "(27) 98120-0880",
        "pos_x": 9866,
        "profissional": "Fernanda Marcenes Kamei",
        "setor": "Unidade de Terapia Intensiva (UTI) Pediátrica",
        "tipo_turno": "Plantão Matutino"
      },
      {
        "data": "20 junho 2026",
        "email": "fernandakamei@gmail.com",
        "horario": "08:00/12:00",
        "phone": "(92) 98113-2728",
        "pos_x": 9866,
        "profissional": "Luiz Felipe Reis Carvalho Sordi",
        "setor": "Unidade de Terapia Intensiva (UTI) Pediátrica",
        "tipo_turno": "Médico Rotineiro I"
      },
      {
        "data": "20 junho 2026",
        "email": "fernandakamei@gmail.com",
        "horario": "13:00/19:00",
        "phone": "(27) 98120-0880",
        "pos_x": 9866,
        "profissional": "Fernanda Marcenes Kamei",
        "setor": "Unidade de Terapia Intensiva (UTI) Pediátrica",
        "tipo_turno": "Plantão Vespertino"
      }
    ],
    "total": 81
  },
  "data_backup": "21/06/2026",
  "hora_backup": "22:36"
}